Workbook

Sheet START HERE
A1: MAJI SAFI — FINANCIAL SOURCE OF TRUTH
A2: Safiflow Ventures Group Limited, t/a Maji Safi · Lukuli Road, Buziga, Kampala
A3: Financial year 1: 1 October 2026 – 30 September 2027
A5: THIS IS THE ONLY FINANCIAL FILE.
A6: If a number is not in here, it is not a number. No side spreadsheets, no second version,
A7: no 'the one on my laptop'. One file, one truth. Everything else is a view OF this file.
A9: HOW IT IS BUILT — four layers
A10: LAYER 1 INPUT You type here and nowhere else:
A11: SETUP · CHART OF ACCOUNTS · COST BOOK · PRICE BOOK · JOURNAL · PAYROLL
A12: LAYER 2 ENGINE Never touched. Computes everything: MONTHLY · P&L · BALANCE SHEET · TvA
A13: LAYER 3 VIEWS One per audience. Read-only. Nobody edits a view:
A14: CO-FOUNDERS · INVESTORS · INTERNAL · TAX (URA) · LENDERS · GROWTH
... A40: WHAT WE STILL DO NOT KNOW → see the GAPS tab. Nothing in here is guessed silently.

Sheet SETUP
A1: SETUP
A2: Blue = you fill it in. This drives dates, tax and opening balances everywhere else.
A4: COMPANY
A5: Registered name | B5: Safiflow Ventures Group Limited
A6: Trading as | B6: Maji Safi
A7: Site | B7: Lukuli Road, Buziga, Makindye, Kampala
A8: FY1 start date | B8: 2026-10-01 | C8: First day of trading. Everything keys off this.
A10: TAX REGISTRATION — see GAPS, several unconfirmed
A11: URA TIN | C11: GAP-01
A12: VAT registered? (YES/NO) | C12: GAP-02 — changes whether output VAT is charged from day 1
A13: VAT effective date | C13: GAP-02
A14: VAT rate | B14: 0.18 | C14: Standard rate
A15: Input VAT recovery assumption | B15: 0.75 | C15: Model assumes 75%. Earned by chasing EFRIS invoices.
A16: EFRIS enrolled? (YES/NO) | C16: GAP-03 — the 75% above depends on this
A17: Excise — ad valorem rate | B17: 0.1 | C17: Law: the HIGHER of this or the specific rate
A18: Excise — specific rate (UGX/litre) | B18: 50 | C18: On a 20L jar the specific rate usually wins
A19: Digital tax stamp (UGX/unit) | B19: 15 | C19: All products, refills included
A20: Corporate income tax rate | B20: 0.3 | C20: Losses carried forward. Accrues monthly, PAID QUARTERLY.
A21: NSSF employee rate | B21: 0.05
A22: NSSF EMPLOYER rate | C22: GAP-04 — model records 5%, statutory is 10%. CONFIRM.
A23: Local Service Tax (KCCA) — in model? | B23: NO | C23: GAP-05 — absent entirely. Needs adding.
A24: Trading licence (KCCA, per year) | B24: 600000
A25: UNBS certification status | C25: GAP-06 — a delay pushes the whole ramp right
A27: OPENING BALANCES AT 1 OCTOBER 2026 — count them, do not estimate
A28: Opening cash — bank | C28: GAP-07 — actual statement balance at 30 Sep
A29: Opening cash — mobile money | C29: GAP-07
A30: Opening cash — petty cash | C30: GAP-07
A31: Opening inventory (counted) | C31: GAP-08 — physical count, not the model's 5,112,500
A32: Jars already in the field at 1 Oct | C32: GAP-09
A33: Deposits already collected at 1 Oct | C33: GAP-09 — this is a liability from day one
A34: Trade receivables at 1 Oct | C34: GAP-10
A35: Trade payables at 1 Oct | C35: GAP-10
A36: Loans outstanding at 1 Oct | C36: GAP-10
A37: Plant and equipment at cost | B37: 315000000 | C37: From the model
A38: Depreciation life (months) | B38: 60 | C38: 5 years. CONFIRM against supplier life — GAP-11
A40: POLICY
A41: MINIMUM CASH FLOOR | B41: 20000000 | C41: Below this, the alarm fires and something gets cut
A42: Variance investigation threshold — % | B42: 0.05 | C42: Investigate any line >5% AND > the amount below
A43: Variance investigation threshold — UGX | B43: 2000000 | C43: Renew gives no rule. This one is ours.
A44: Monthly close deadline | B44: 10th | C44: Renew: 'Close on the 10th!'
A45: Monthly report to readers | B45: 15th | C45: One page, LEAD format, same day every month

Sheet CHART OF ACCOUNTS
A1: CHART OF ACCOUNTS
A2: The controlled vocabulary. Add a line HERE before using it in JOURNAL. This is what migrates to Xero/QuickBooks.
A4: Code | B4: Account name | C4: Class | D4: Statement | E4: VAT code | F4: Notes
A5: 1000 | B5: Cash — bank | C5: Asset | D5: Balance Sheet | E5: N/A
A6: 1010 | B6: Cash — mobile money | C6: Asset | D6: Balance Sheet | E6: N/A | F6: MTN / Airtel merchant
A7: 1020 | B7: Cash — petty cash | C7: Asset | D7: Balance Sheet | E7: N/A
A8: 1100 | B8: Trade receivables | C8: Asset | D8: Balance Sheet | E8: N/A | F8: Zero in the plan. Will not stay zero.
A9: 1200 | B9: Inventory — preforms and bottles | C9: Asset | D9: Balance Sheet | E9: Std
A10: 1210 | B10: Inventory — caps and labels | C10: Asset | D10: Balance Sheet | E10: Std
A11: 1220 | B11: Inventory — jars held for issue | C11: Asset | D11: Balance Sheet | E11: Std
A12: 1230 | B12: Inventory — treatment consumables | C12: Asset | D12: Balance Sheet | E12: Std | F12: Membranes, filters, chemicals
A13: 1300 | B13: Input VAT recoverable | C13: Asset | D13: Balance Sheet | E13: N/A | F13: The 75%/90% recovery lives here
A14: 1500 | B14: Plant and equipment at cost | C14: Asset | D14: Balance Sheet | E14: Std
A15: 1510 | B15: Accumulated depreciation | C15: Asset | D15: Balance Sheet | E15: N/A | F15: Contra-asset
A16: 2000 | B16: Trade payables | C16: Liability | D16: Balance Sheet | E16: N/A | F16: Zero in the plan
A17: 2100 | B17: CUSTOMER DEPOSITS — refundable | C17: Liability | D17: Balance Sheet | E17: N/A | F17: NOT revenue. Our largest liability.
A18: 2200 | B18: Output VAT payable | C18: Liability | D18: Balance Sheet | E18: N/A | F18: Collected for URA
A19: 2210 | B19: Excise duty payable | C19: Liability | D19: Balance Sheet | E19: N/A | F19: Collected for URA
A20: 2220 | B20: Digital tax stamps payable | C20: Liability | D20: Balance Sheet | E20: N/A
A21: 2300 | B21: PAYE payable | C21: Liability | D21: Balance Sheet | E21: N/A | F21: Withheld from wages
A22: 2310 | B22: NSSF payable | C22: Liability | D22: Balance Sheet | E22: N/A | F22: Employee + employer
A23: 2320 | B23: Local Service Tax payable | C23: Liability | D23: Balance Sheet | E23: N/A | F23: GAP-05 — not yet modelled
A24: 2400 | B24: Corporate tax payable | C24: Liability | D24: Balance Sheet | E24: N/A | F24: Accrues monthly, paid quarterly
A25: 2500 | B25: Loans and borrowings | C25: Liability | D25: Balance Sheet | E25: N/A | F25: None today
A26: 3000 | B26: Share capital | C26: Equity | D26: Balance Sheet | E26: N/A | F26: GAP-12 — real cap table unknown
A27: 3100 | B27: Retained earnings | C27: Equity | D27: Balance Sheet | E27: N/A
A28: 4000 | B28: Revenue — 20L refill | C28: Revenue | D28: P&L | E28: Std | F28: NET of VAT and excise
A29: 4010 | B29: Revenue — 20L single-use | C29: Revenue | D29: P&L | E29: Std
A30: 4020 | B30: Revenue — 5L single-use | C30: Revenue | D30: P&L | E30: Std
A31: 4100 | B31: Revenue — delivery charges | C31: Revenue | D31: P&L | E31: Std | F31: If charged separately
A32: 5000 | B32: COGS — preforms and bottles | C32: Cost of sales | D32: P&L | E32: Std | F32: GAP-13 — need the bill of materials
A33: 5010 | B33: COGS — caps, labels, shrink wrap | C33: Cost of sales | D33: P&L | E33: Std | F33: GAP-13
A34: 5020 | B34: COGS — treatment chemicals | C34: Cost of sales | D34: P&L | E34: Std | F34: GAP-13
A35: 5030 | B35: COGS — membranes and filters | C35: Cost of sales | D35: P&L | E35: Std | F35: GAP-13 + GAP-11
A36: 5040 | B36: COGS — plant electricity and water | C36: Cost of sales | D36: P&L | E36: Std | F36: GAP-13
A37: 5050 | B37: COGS — digital tax stamps | C37: Cost of sales | D37: P&L | E37: N/A | F37: 15 UGX per unit
A38: 5100 | B38: JAR COST expensed on issue | C38: Cost of sales | D38: P&L | E38: Std | F38: 11,000/jar. Expensed, never capitalised.
A39: 5200 | B39: Delivery and logistics | C39: Cost of sales | D39: P&L | E39: Std | F39: GAP-14 — own vehicles or hired?
A40: 6000 | B40: Salaries and wages | C40: Operating cost | D40: P&L | E40: N/A | F40: GAP-15 — need the headcount register
A41: 6010 | B41: NSSF — employer contribution | C41: Operating cost | D41: P&L | E41: N/A | F41: GAP-04
A42: 6100 | B42: Rent | C42: Operating cost | D42: P&L | E42: Std | F42: GAP-16 — part of the 8,163,542 blend
... A56: 9000 | B56: Bad debt provision | C56: Operating cost | D56: P&L | E56: N/A | F56: Zero today. Will not stay zero.

Sheet COST BOOK
A1: COST BOOK — every cost we have, and what we do not yet know
A2: What we know comes from the Year-1 model. What we do not know is marked NEEDS BREAKDOWN and carried to GAPS. Nothing here is invented.
A4: Code | B4: Cost line | C4: Category | D4: FY1 amount (UGX) | E4: Basis | F4: Owner | G4: Status / what is missing
A5: 5000-5050 | B5: Cost of sales — all materials and plant inputs | C5: Cost of sales | D5: 1091364454 | E5: Per unit: 3,884 in M1 falling to 2,132 by M12 | F5: Sammy | G5: NEEDS BREAKDOWN — one blended number. Need the bill of materials per SKU: preforms, caps, labels, shrink, chemicals, membranes, plant power, water.
A6: 5100 | B6: Jar cost expensed on issue | C6: Cost of sales | D6: 99000000 | E6: 750 jars x 11,000 per month | F6: Sammy | G6: KNOWN and firm
A7: 5200 | B7: Delivery and logistics | C7: Cost of sales | E7: Unknown | F7: Sammy | G7: MISSING — is delivery inside the COGS blend or not budgeted at all? Own vehicles or hired? Fuel, driver, maintenance?
A8: 6000 | B8: Salaries and wages | C8: Operating | D8: 118900000 | E8: 2,575,000/mo, stepping to 13,575,000 at month 5 | F8: Sammy | G8: NEEDS BREAKDOWN — how many heads at each step, which roles, which are production vs admin?
A9: 6010 | B9: NSSF employer contribution | C9: Operating | E9: 5% recorded; statutory 10% | F9: Sammy | G9: UNDERSTATED — confirm the rate, then this line roughly doubles
A10: 6100-6210 | B10: Fixed operating costs — all overheads | C10: Operating | D10: 97962504 | E10: 8,163,542 per month, flat | F10: Sammy | G10: NEEDS BREAKDOWN — one blended number covering rent, power, security, internet, insurance, repairs, cleaning, licence, professional fees. We know only two pieces: licence 600,000/yr and insurance approx 150,000/mo.
A11: 6190 | B11: Marketing and customer acquisition | C11: Operating | E11: Not in the model | F11: Sammy | G11: MISSING ENTIRELY — the plan acquires 750 new jar customers every month with zero acquisition cost. That cannot be right.
A12: 6200 | B12: Transaction and bank fees | C12: Operating | D12: 12742413 | E12: 0.5% of gross billings | F12: Sammy | G12: KNOWN
A13: 7000 | B13: Depreciation | C13: Operating | D13: 63000000 | E13: 315,000,000 over 60 months | F13: Sammy | G13: KNOWN — but confirm the 5-year life and add membrane replacement
A14: 5030 | B14: Membrane and filter replacement | C14: Cost of sales | E14: Not in the model | F14: Sammy | G14: MISSING — zero maintenance capex and zero consumables replacement in a full year of running 2,000 jars/day
A15: 8000 | B15: Corporate income tax | C15: Tax | D15: 97467102 | E15: 30% of taxable profit, paid quarterly | F15: Sammy | G15: KNOWN
A16: 2200-2220 | B16: VAT, excise and digital stamps | C16: Collected for URA | D16: 740623047 | E16: 29.1% of gross billings | F16: Sammy | G16: KNOWN — and never ours
A17: 2320 | B17: Local Service Tax | C17: Tax | E17: KCCA, on employees | F17: Sammy | G17: MISSING ENTIRELY from the model
A18: 6170 | B18: Trading licence | C18: Operating | D18: 600000 | E18: KCCA per year | F18: Sammy | G18: KNOWN
A19: 9000 | B19: Bad debt provision | C19: Operating | E19: Zero — every sale is cash | F19: Sammy | G19: NOT PROVIDED — fine while DSO is 0. The first institution on 30 days changes that.
A20: 2100 | B20: Jar deposit REFUNDS | C20: Balance sheet | E20: Zero returns assumed | F20: Sammy | G20: MISSING — no return rate, no refund reserve, no forfeiture policy
B22: TOTAL COSTS WE CAN NAME (FY1) | D22: =SUM(D5:D20)
B24: Six lines above have no number at all. Four more are single blended figures hiding many lines.
B25: Until those are broken out we do not actually know our costs — we know our cost TOTAL, which is not the same thing.
B26: Renew Session 3: a gap on its own is not a finding. The reason behind it is. You cannot find a reason inside a blended number.

Sheet PRICE BOOK
A1: PRICE BOOK — two books, decided by one question: who moves the water?
A3: Product | B3: B2B floor | C3: B2B list | D3: B2C | E3: Status | F3: Notes
A4: 20L Refill | B4: 3300 | C4: 5000 | D4: 6000 | E4: ANCHORS SET | F4: Sammy, 8 Sep 2026
A5: 20L Single-Use | B5: 9000 | C5: 10050 | D5: 10350 | E5: ANCHORS SET
A6: 5L Single-Use | B6: 3450 | C6: 4500 | D6: 4800 | E6: ANCHORS SET
A7: 20L Reusable Jar (DEPOSIT) | B7: 16800 | C7: 17850 | D7: 18150 | E7: NEVER DISCOUNTED | F7: A liability, not revenue
A9: B2B VOLUME LADDER — tier set from LAST MONTH'S ACHIEVED volume, never a promise
A10: Achieved last month | B10: 20L Refill | C10: 20L Single-Use | D10: 5L | E10: Status
A11: List (base) | B11: 5000 | C11: 10050 | D11: 4500 | E11: APPROVED — Sammy 8 Sep
A12: 500+ | B12: 4400 | C12: 9700 | D12: 4150 | E12: NOT APPROVED — GAP-19
A13: 1,500+ | B13: 3800 | C13: 9350 | D13: 3800 | E13: NOT APPROVED — GAP-19
A14: 3,000+ (FLOOR) | B14: 3300 | C14: 9000 | D14: 3450 | E14: APPROVED — never below
A16: Half this ladder is still unapproved, so part of our revenue mix is assumption. And 'the floor is earned' is a sentence, not a control — nothing stops someone granting it in the moment.

Sheet JOURNAL
A1: JOURNAL — every transaction, double entry. This is the whole data-entry job.
A2: One row per side. Debits equal credits. Pick the account code from CHART OF ACCOUNTS — never type a new name here.
A4: Date | B4: Ref | C4: Account code | D4: Account name | E4: Description | F4: Counterparty | G4: Channel | H4: Product | I4: Debit | J4: Credit | K4: VAT code | L4: Source doc | M4: Entered by
D5: =IFERROR(VLOOKUP($C5,'CHART OF ACCOUNTS'!$A:$B,2,FALSE),"")
D6: =IFERROR(VLOOKUP($C6,'CHART OF ACCOUNTS'!$A:$B,2,FALSE),"")
D7: =IFERROR(VLOOKUP($C7,'CHART OF ACCOUNTS'!$A:$B,2,FALSE),"")
D8: =IFERROR(VLOOKUP($C8,'CHART OF ACCOUNTS'!$A:$B,2,FALSE),"")
D9: =IFERROR(VLOOKUP($C9,'CHART OF ACCOUNTS'!$A:$B,2,FALSE),"")
D10: =IFERROR(VLOOKUP($C10,'CHART OF ACCOUNTS'!$A:$B,2,FALSE),"")
D11: =IFERROR(VLOOKUP($C11,'CHART OF ACCOUNTS'!$A:$B,2,FALSE),"")
D12: =IFERROR(VLOOKUP($C12,'CHART OF ACCOUNTS'!$A:$B,2,FALSE),"")
D13: =IFERROR(VLOOKUP($C13,'CHART OF ACCOUNTS'!$A:$B,2,FALSE),"")
D14: =IFERROR(VLOOKUP($C14,'CHART OF ACCOUNTS'!$A:$B,2,FALSE),"")
D15: =IFERROR(VLOOKUP($C15,'CHART OF ACCOUNTS'!$A:$B,2,FALSE),"")
D16: =IFERROR(VLOOKUP($C16,'CHART OF ACCOUNTS'!$A:$B,2,FALSE),"")
... D504: =IFERROR(VLOOKUP($C504,'CHART OF ACCOUNTS'!$A:$B,2,FALSE),"")

Sheet MONTHLY
A1: MONTHLY — engine. Never type here.
A2: Net movement per account per month, built from JOURNAL with SUMIFS. Debit positive, credit negative.
A4: Code | B4: Account | C4: Oct-26 | D4: Nov-26 | E4: Dec-26 | F4: Jan-27 | G4: Feb-27 | H4: Mar-27 | I4: Apr-27 | J4: May-27 | K4: Jun-27 | L4: Jul-27 | M4: Aug-27 | N4: Sep-27 | O4: FY1 TOTAL
A5: 1000 | B5: Cash — bank | C5: =SUMIFS(JOURNAL!$I$5:$I$504,JOURNAL!$C$5:$C$504,$A5,JOURNAL!$A$5:$A$504,">="&DATE(YEAR(SETUP!$B$8),MONTH(SETUP!$B$8)+0,1),JOURNAL!$A$5:$A$504,"<="&EOMONTH(SETUP!$B$8,0))-SUMIFS(JOURNAL!$J$5:$J$504,JOURNAL!$C$5:$C$504,$A5,JOURNAL!$A$5:$A$504,">="&DATE(YEAR(SETUP!$B$8),MONTH(SETUP!$B$8)+0,1),JOURNAL!$A$5:$A$504,"<="&EOMONTH(SETUP!$B$8,0)) | D5: =SUMIFS(JOURNAL!$I$5:$I$504,JOURNAL!$C$5:$C$504,$A5,JOURNAL!$A$5:$A$504,">="&DATE(YEAR(SETUP!$B$8),MONTH(SETUP!$B$8)+1,1),JOURNAL!$A$5:$A$504,"<="&EOMONTH(SETUP!$B$8,1))-SUMIFS(JOURNAL!$J$5:$J$504,JOURNAL!$C$5:$C$504,$A5,JOURNAL!$A$5:$A$504,">="&DATE(YEAR(SETUP!$B$8),MONTH(SETUP!$B$8)+1,1),JOURNAL!$A$5:$A$504,"<="&EOMONTH(SETUP!$B$8,1)) | E5: =SUMIFS(JOURNAL!$I$5:$I$504,JOURNAL!$C$5:$C$504,$A5,JOURNAL!$A$5:$A$504,">="&DATE(YEAR(SETUP!$B$8),MONTH(SETUP!$B$8)+2,1),JOURNAL!$A$5:$A$504,"<="&EOMONTH(SETUP!$B$8,2))-SUMIFS(JOURNAL!$J$5:$J$504,JOURNAL!$C$5:$C$504,$A5,JOURNAL!$A$5:$A$504,">="&DATE(YEAR(SETUP!$B$8),MONTH(SETUP!$B$8)+2,1),JOURNAL!$A$5:$A$504,"<="&EOMONTH(SETUP!$B$8,2)) | F5: =SUMIFS(JOURNAL!$I$5:$I$504,JOURNAL!$C$5:$C$504,$A5,JOURNAL!$A$5:$A$504,">="&DATE(YEAR(SETUP!$B$8),MONTH(SETUP!$B$8)+3,1),JOURNAL!$A$5:$A$504,"<="&EOMONTH(SETUP!$B$8,3))-SUMIFS(JOURNAL!$J$5:$J$504,JOURNAL!$C$5:$C$504,$A5,JOURNAL!$A$5:$A$504,">="&DATE(YEAR(SETUP!$B$8),MONTH(SETUP!$B$8)+3,1),JOURNAL!$A$5:$A$504,"<="&EOMONTH(SETUP!$B$8,3)) | G5: =SUMIFS(JOURNAL!$I$5:$I$504,JOURNAL!$C$5:$C$504,$A5,JOURNAL!$A$5:$A$504,">="&DATE(YEAR(SETUP!$B$8),MONTH(SETUP!$B$8)+4,1),JOURNAL!$A$5:$A$504,"<="&EOMONTH(SETUP!$B$8,4))-SUMIFS(JOURNAL!$J$5:$J$504,JOURNAL!$C$5:$C$504,$A5,JOURNAL!$A$5:$A$504,">="&DATE(YEAR(SETUP!$B$8),MONTH(SETUP!$B$8)+4,1),JOURNAL!$A$5:$A$504,"<="&EOMONTH(SETUP!$B$8,4)) | H5: =SUMIFS(JOURNAL!$I$5:$I$504,JOURNAL!$C$5:$C$504,$A5,JOURNAL!$A$5:$A$504,">="&DATE(YEAR(SETUP!$B$8),MONTH(SETUP!$B$8)+5,1),JOURNAL!$A$5:$A$504,"<="&EOMONTH(SETUP!$B$8,5))-SUMIFS(JOURNAL!$J$5:$J$504,JOURNAL!$C$5:$C$504,$A5,JOURNAL!$A$5:$A$504,">="&DATE(YEAR(SETUP!$B$8),MONTH(SETUP!$B$8)+5,1),JOURNAL!$A$5:$A$504,"<="&EOMONTH(SETUP!$B$8,5)) | I5: =SUMIFS(JOURNAL!$I$5:$I$504,JOURNAL!$C$5:$C$504,$A5,JOURNAL!$A$5:$A$504,">="&DATE(YEAR(SETUP!$B$8),MONTH(SETUP!$B$8)+6,1),JOURNAL!$A$5:$A$504,"<="&EOMONTH(SETUP!$B$8,6))-SUMIFS(JOURNAL!$J$5:$J$504,JOURNAL!$C$5:$C$504,$A5,JOURNAL!$A$5:$A$504,">="&DATE(YEAR(SETUP!$B$8),MONTH(SETUP!$B$8)+6,1),JOURNAL!$A$5:$A$504,"<="&EOMONTH(SETUP!$B$8,6)) | J5: =SUMIFS(JOURNAL!$I$5:$I$504,JOURNAL!$C$5:$C$504,$A5,JOURNAL!$A$5:$A$504,">="&DATE(YEAR(SETUP!$B$8),MONTH(SETUP!$B$8)+7,1),JOURNAL!$A$5:$A$504,"<="&EOMONTH(SETUP!$B$8,7))-SUMIFS(JOURNAL!$J$5:$J$504,JOURNAL!$C$5:$C$504,$A5,JOURNAL!$A$5:$A$504,">="&DATE(YEAR(SETUP!$B$8),MONTH(SETUP!$B$8)+7,1),JOURNAL!$A$5:$A$504,"<="&EOMONTH(SETUP!$B$8,7)) | K5: =SUMIFS(JOURNAL!$I$5:$I$504,JOURNAL!$C$5:$C$504,$A5,JOURNAL!$A$5:$A$504,">="&DATE(YEAR(SETUP!$B$8),MONTH(SETUP!$B$8)+8,1),JOURNAL!$A$5:$A$504,"<="&EOMONTH(SETUP!$B$8,8))-SUMIFS(JOURNAL!$J$5:$J$504,JOURNAL!$C$5:$C$504,$A5,JOURNAL!$A$5:$A$504,">="&DATE(YEAR(SETUP!$B$8),MONTH(SETUP!$B$8)+8,1),JOURNAL!$A$5:$A$504,"<="&EOMONTH(SETUP!$B$8,8)) | L5: =SUMIFS(JOURNAL!$I$5:$I$504,JOURNAL!$C$5:$C$504,$A5,JOURNAL!$A$5:$A$504,">="&DATE(YEAR(SETUP!$B$8),MONTH(SETUP!$B$8)+9,1),JOURNAL!$A$5:$A$504,"<="&EOMONTH(SETUP!$B$8,9))-SUMIFS(JOURNAL!$J$5:$J$504,JOURNAL!$C$5:$C$504,$A5,JOURNAL!$A$5:$A$504,">="&DATE(YEAR(SETUP!$B$8),MONTH(SETUP!$B$8)+9,1),JOURNAL!$A$5:$A$504,"<="&EOMONTH(SETUP!$B$8,9)) | M5: =SUMIFS(JOURNAL!$I$5:$I$504,JOURNAL!$C$5:$C$504,$A5,JOURNAL!$A$5:$A$504,">="&DATE(YEAR(SETUP!$B$8),MONTH(SETUP!$B$8)+10,1),JOURNAL!$A$5:$A$504,"<="&EOMONTH(SETUP!$B$8,10))-SUMIFS(JOURNAL!$J$5:$J$504,JOURNAL!$C$5:$C$504,$A5,JOURNAL!$A$5:$A$504,">="&DATE(YEAR(SETUP!$B$8),MONTH(SETUP!$B$8)+10,1),JOURNAL!$A$5:$A$504,"<="&EOMONTH(SETUP!$B$8,10)) | N5: =SUMIFS(JOURNAL!$I$5:$I$504,JOURNAL!$C$5:$C$504,$A5,JOURNAL!$A$5:$A$504,">="&DATE(YEAR(SETUP!$B$8),MONTH(SETUP!$B$8)+11,1),JOURNAL!$A$5:$A$504,"<="&EOMONTH(SETUP!$B$8,11))-SUMIFS(JOURNAL!$J$5:$J$504,JOURNAL!$C$5:$C$504,$A5,JOURNAL!$A$5:$A$504,">="&DATE(YEAR(SETUP!$B$8),MONTH(SETUP!$B$8)+11,1),JOURNAL!$A$5:$A$504,"<="&EOMONTH(SETUP!$B$8,11)) | O5: =SUM(C5:N5)
A6: 1010 | B6: Cash — mobile money | C6: =SUMIFS(JOURNAL!$I$5:$I$504,JOURNAL!$C$5:$C$504,$A6,JOURNAL!$A$5:$A$504,">="&DATE(YEAR(SETUP!$B$8),MONTH(SETUP!$B$8)+0,1),JOURNAL!$A$5:$A$504,"<="&EOMONTH(SETUP!$B$8,0))-SUMIFS(JOURNAL!$J$5:$J$504,JOURNAL!$C$5:$C$504,$A6,JOURNAL!$A$5:$A$504,">="&DATE(YEAR(SETUP!$B$8),MONTH(SETUP!$B$8)+0,1),JOURNAL!$A$5:$A$504,"<="&EOMONTH(SETUP!$B$8,0)) | D6: =SUMIFS(JOURNAL!$I$5:$I$504,JOURNAL!$C$5:$C$504,$A6,JOURNAL!$A$5:$A$504,">="&DATE(YEAR(SETUP!$B$8),MONTH(SETUP!$B$8)+1,1),JOURNAL!$A$5:$A$504,"<="&EOMONTH(SETUP!$B$8,1))-SUMIFS(JOURNAL!$J$5:$J$504,JOURNAL!$C$5:$C$504,$A6,JOURNAL!$A$5:$A$504,">="&DATE(YEAR(SETUP!$B$8),MONTH(SETUP!$B$8)+1,1),JOURNAL!$A$5:$A$504,"<="&EOMONTH(SETUP!$B$8,1)) | E6: =SUMIFS(JOURNAL!$I$5:$I$504,JOURNAL!$C$5:$C$504,$A6,JOURNAL!$A$5:$A$504,">="&DATE(YEAR(SETUP!$B$8),MONTH(SETUP!$B$8)+2,1),JOURNAL!$A$5:$A$504,"<="&EOMONTH(SETUP!$B$8,2))-SUMIFS(JOURNAL!$J$5:$J$504,JOURNAL!$C$5:$C$504,$A6,JOURNAL!$A$5:$A$504,">="&DATE(YEAR(SETUP!$B$8),MONTH(SETUP!$B$8)+2,1),JOURNAL!$A$5:$A$504,"<="&EOMONTH(SETUP!$B$8,2)) | F6: =SUMIFS(JOURNAL!$I$5:$I$504,JOURNAL!$C$5:$C$504,$A6,JOURNAL!$A$5:$A$504,">="&DATE(YEAR(SETUP!$B$8),MONTH(SETUP!$B$8)+3,1),JOURNAL!$A$5:$A$504,"<="&EOMONTH(SETUP!$B$8,3))-SUMIFS(JOURNAL!$J$5:$J$504,JOURNAL!$C$5:$C$504,$A6,JOURNAL!$A$5:$A$504,">="&DATE(YEAR(SETUP!$B$8),MONTH(SETUP!$B$8)+3,1),JOURNAL!$A$5:$A$504,"<="&EOMONTH(SETUP!$B$8,3)) | G6: =SUMIFS(JOURNAL!$I$5:$I$504,JOURNAL!$C$5:$C$504,$A6,JOURNAL!$A$5:$A$504,">="&DATE(YEAR(SETUP!$B$8),MONTH(SETUP!$B$8)+4,1),JOURNAL!$A$5:$A$504,"<="&EOMONTH(SETUP!$B$8,4))-SUMIFS(JOURNAL!$J$5:$J$504,JOURNAL!$C$5:$C$504,$A6,JOURNAL!$A$5:$A$504,">="&DATE(YEAR(SETUP!$B$8),MONTH(SETUP!$B$8)+4,1),JOURNAL!$A$5:$A$504,"<="&EOMONTH(SETUP!$B$8,4)) | H6: =SUMIFS(JOURNAL!$I$5:$I$504,JOURNAL!$C$5:$C$504,$A6,JOURNAL!$A$5:$A$504,">="&DATE(YEAR(SETUP!$B$8),MONTH(SETUP!$B$8)+5,1),JOURNAL!$A$5:$A$504,"<="&EOMONTH(SETUP!$B$8,5))-SUMIFS(JOURNAL!$J$5:$J$504,JOURNAL!$C$5:$C$504,$A6,JOURNAL!$A$5:$A$504,">="&DATE(YEAR(SETUP!$B$8),MONTH(SETUP!$B$8)+5,1),JOURNAL!$A$5:$A$504,"<="&EOMONTH(SETUP!$B$8,5)) | I6: =SUMIFS(JOURNAL!$I$5:$I$504,JOURNAL!$C$5:$C$504,$A6,JOURNAL!$A$5:$A$504,">="&DATE(YEAR(SETUP!$B$8),MONTH(SETUP!$B$8)+6,1),JOURNAL!$A$5:$A$504,"<="&EOMONTH(SETUP!$B$8,6))-SUMIFS(JOURNAL!$J$5:$J$504,JOURNAL!$C$5:$C$504,$A6,JOURNAL!$A$5:$A$504,">="&DATE(YEAR(SETUP!$B$8),MONTH(SETUP!$B$8)+6,1),JOURNAL!$A$5:$A$504,"<="&EOMONTH(SETUP!$B$8,6)) | J6: =SUMIFS(JOURNAL!$I$5:$I$504,JOURNAL!$C$5:$C$504,$A6,JOURNAL!$A$5:$A$504,">="&DATE(YEAR(SETUP!$B$8),MONTH(SETUP!$B$8)+7,1),JOURNAL!$A$5:$A$504,"<="&EOMONTH(SETUP!$B$8,7))-SUMIFS(JOURNAL!$J$5:$J$504,JOURNAL!$C$5:$C$504,$A6,JOURNAL!$A$5:$A$504,">="&DATE(YEAR(SETUP!$B$8),MONTH(SETUP!$B$8)+7,1),JOURNAL!$A$5:$A$504,"<="&EOMONTH(SETUP!$B$8,7)) | K6: =SUMIFS(JOURNAL!$I$5:$I$504,JOURNAL!$C$5:$C$504,$A6,JOURNAL!$A$5:$A$504,">="&DATE(YEAR(SETUP!$B$8),MONTH(SETUP!$B$8)+8,1),JOURNAL!$A$5:$A$504,"<="&EOMONTH(SETUP!$B$8,8))-SUMIFS(JOURNAL!$J$5:$J$504,JOURNAL!$C$5:$C$504,$A6,JOURNAL!$A$5:$A$504,">="&DATE(YEAR(SETUP!$B$8),MONTH(SETUP!$B$8)+8,1),JOURNAL!$A$5:$A$504,"<="&EOMONTH(SETUP!$B$8,8)) | L6: =SUMIFS(JOURNAL!$I$5:$I$504,JOURNAL!$C$5:$C$504,$A6,JOURNAL!$A$5:$A$504,">="&DATE(YEAR(SETUP!$B$8),MONTH(SETUP!$B$8)+9,1),JOURNAL!$A$5:$A$504,"<="&EOMONTH(SETUP!$B$8,9))-SUMIFS(JOURNAL!$J$5:$J$504,JOURNAL!$C$5:$C$504,$A6,JOURNAL!$A$5:$A$504,">="&DATE(YEAR(SETUP!$B$8),MONTH(SETUP!$B$8)+9,1),JOURNAL!$A$5:$A$504,"<="&EOMONTH(SETUP!$B$8,9)) | M6: =SUMIFS(JOURNAL!$I$5:$I$504,JOURNAL!$C$5:$C$504,$A6,JOURNAL!$A$5:$A$504,">="&DATE(YEAR(SETUP!$B$8),MONTH(SETUP!$B$8)+10,1),JOURNAL!$A$5:$A$504,"<="&EOMONTH(SETUP!$B$8,10))-SUMIFS(JOURNAL!$J$5:$J$504,JOURNAL!$C$5:$C$504,$A6,JOURNAL!$A$5:$A$504,">="&DATE(YEAR(SETUP!$B$8),MONTH(SETUP!$B$8)+10,1),JOURNAL!$A$5:$A$504,"<="&EOMONTH(SETUP!$B$8,10)) | N6: =SUMIFS(JOURNAL!$I$5:$I$504,JOURNAL!$C$5:$C$504,$A6,JOURNAL!$A$5:$A$504,">="&DATE(YEAR(SETUP!$B$8),MONTH(SETUP!$B$8)+11,1),JOURNAL!$A$5:$A$504,"<="&EOMONTH(SETUP!$B$8,11))-SUMIFS(JOURNAL!$J$5:$J$504,JOURNAL!$C$5:$C$504,$A6,JOURNAL!$A$5:$A$504,">="&DATE(YEAR(SETUP!$B$8),MONTH(SETUP!$B$8)+11,1),JOURNAL!$A$5:$A$504,"<="&EOMONTH(SETUP!$B$8,11)) | O6: =SUM(C6:N6)
A7: 1020 | B7: Cash — petty cash | C7: =SUMIFS(JOURNAL!$I$5:$I$504,JOURNAL!$C$5:$C$504,$A7,JOURNAL!$A$5:$A$504,">="&DATE(YEAR(SETUP!$B$8),MONTH(SETUP!$B$8)+0,1),JOURNAL!$A$5:$A$504,"<="&EOMONTH(SETUP!$B$8,0))-SUMIFS(JOURNAL!$J$5:$J$504,JOURNAL!$C$5:$C$504,$A7,JOURNAL!$A$5:$A$504,">="&DATE(YEAR(SETUP!$B$8),MONTH(SETUP!$B$8)+0,1),JOURNAL!$A$5:$A$504,"<="&EOMONTH(SETUP!$B$8,0)) | D7: =SUMIFS(JOURNAL!$I$5:$I$504,JOURNAL!$C$5:$C$504,$A7,JOURNAL!$A$5:$A$504,">="&DATE(YEAR(SETUP!$B$8),MONTH(SETUP!$B$8)+1,1),JOURNAL!$A$5:$A$504,"<="&EOMONTH(SETUP!$B$8,1))-SUMIFS(JOURNAL!$J$5:$J$504,JOURNAL!$C$5:$C$504,$A7,JOURNAL!$A$5:$A$504,">="&DATE(YEAR(SETUP!$B$8),MONTH(SETUP!$B$8)+1,1),JOURNAL!$A$5:$A$504,"<="&EOMONTH(SETUP!$B$8,1)) | E7: =SUMIFS(JOURNAL!$I$5:$I$504,JOURNAL!$C$5:$C$504,$A7,JOURNAL!$A$5:$A$504,">="&DATE(YEAR(SETUP!$B$8),MONTH(SETUP!$B$8)+2,1),JOURNAL!$A$5:$A$504,"<="&EOMONTH(SETUP!$B$8,2))-SUMIFS(JOURNAL!$J$5:$J$504,JOURNAL!$C$5:$C$504,$A7,JOURNAL!$A$5:$A$504,">="&DATE(YEAR(SETUP!$B$8),MONTH(SETUP!$B$8)+2,1),JOURNAL!$A$5:$A$504,"<="&EOMONTH(SETUP!$B$8,2)) | F7: =SUMIFS(JOURNAL!$I$5:$I$504,JOURNAL!$C$5:$C$504,$A7,JOURNAL!$A$5:$A$504,">="&DATE(YEAR(SETUP!$B$8),MONTH(SETUP!$B$8)+3,1),JOURNAL!$A$5:$A$504,"<="&EOMONTH(SETUP!$B$8,3))-SUMIFS(JOURNAL!$J$5:$J$504,JOURNAL!$C$5:$C$504,$A7,JOURNAL!$A$5:$A$504,">="&DATE(YEAR(SETUP!$B$8),MONTH(SETUP!$B$8)+3,1),JOURNAL!$A$5:$A$504,"<="&EOMONTH(SETUP!$B$8,3)) | G7: =SUMIFS(JOURNAL!$I$5:$I$504,JOURNAL!$C$5:$C$504,$A7,JOURNAL!$A$5:$A$504,">="&DATE(YEAR(SETUP!$B$8),MONTH(SETUP!$B$8)+4,1),JOURNAL!$A$5:$A$504,"<="&EOMONTH(SETUP!$B$8,4))-SUMIFS(JOURNAL!$J$5:$J$504,JOURNAL!$C$5:$C$504,$A7,JOURNAL!$A$5:$A$504,">="&DATE(YEAR(SETUP!$B$8),MONTH(SETUP!$B$8)+4,1),JOURNAL!$A$5:$A$504,"<="&EOMONTH(SETUP!$B$8,4)) | H7: =SUMIFS(JOURNAL!$I$5:$I$504,JOURNAL!$C$5:$C$504,$A7,JOURNAL!$A$5:$A$504,">="&DATE(YEAR(SETUP!$B$8),MONTH(SETUP!$B$8)+5,1),JOURNAL!$A$5:$A$504,"<="&EOMONTH(SETUP!$B$8,5))-SUMIFS(JOURNAL!$J$5:$J$504,JOURNAL!$C$5:$C$504,$A7,JOURNAL!$A$5:$A$504,">="&DATE(YEAR(SETUP!$B$8),MONTH(SETUP!$B$8)+5,1),JOURNAL!$A$5:$A$504,"<="&EOMONTH(SETUP!$B$8,5)) | I7: =SUMIFS(JOURNAL!$I$5:$I$504,JOURNAL!$C$5:$C$504,$A7,JOURNAL!$A$5:$A$504,">="&DATE(YEAR(SETUP!$B$8),MONTH(SETUP!$B$8)+6,1),JOURNAL!$A$5:$A$504,"<="&EOMONTH(SETUP!$B$8,6))-SUMIFS(JOURNAL!$J$5:$J$504,JOURNAL!$C$5:$C$504,$A7,JOURNAL!$A$5:$A$504,">="&DATE(YEAR(SETUP!$B$8),MONTH(SETUP!$B$8)+6,1),JOURNAL!$A$5:$A$504,"<="&EOMONTH(SETUP!$B$8,6)) | J7: =SUMIFS(JOURNAL!$I$5:$I$504,JOURNAL!$C$5:$C$504,$A7,JOURNAL!$A$5:$A$504,">="&DATE(YEAR(SETUP!$B$8),MONTH(SETUP!$B$8)+7,1),JOURNAL!$A$5:$A$504,"<="&EOMONTH(SETUP!$B$8,7))-SUMIFS(JOURNAL!$J$5:$J$504,JOURNAL!$C$5:$C$504,$A7,JOURNAL!$A$5:$A$504,">="&DATE(YEAR(SETUP!$B$8),MONTH(SETUP!$B$8)+7,1),JOURNAL!$A$5:$A$504,"<="&EOMONTH(SETUP!$B$8,7)) | K7: =SUMIFS(JOURNAL!$I$5:$I$504,JOURNAL!$C$5:$C$504,$A7,JOURNAL!$A$5:$A$504,">="&DATE(YEAR(SETUP!$B$8),MONTH(SETUP!$B$8)+8,1),JOURNAL!$A$5:$A$504,"<="&EOMONTH(SETUP!$B$8,8))-SUMIFS(JOURNAL!$J$5:$J$504,JOURNAL!$C$5:$C$504,$A7,JOURNAL!$A$5:$A$504,">="&DATE(YEAR(SETUP!$B$8),MONTH(SETUP!$B$8)+8,1),JOURNAL!$A$5:$A$504,"<="&EOMONTH(SETUP!$B$8,8)) | L7: =SUMIFS(JOURNAL!$I$5:$I$504,JOURNAL!$C$5:$C$504,$A7,JOURNAL!$A$5:$A$504,">="&DATE(YEAR(SETUP!$B$8),MONTH(SETUP!$B$8)+9,1),JOURNAL!$A$5:$A$504,"<="&EOMONTH(SETUP!$B$8,9))-SUMIFS(JOURNAL!$J$5:$J$504,JOURNAL!$C$5:$C$504,$A7,JOURNAL!$A$5:$A$504,">="&DATE(YEAR(SETUP!$B$8),MONTH(SETUP!$B$8)+9,1),JOURNAL!$A$5:$A$504,"<="&EOMONTH(SETUP!$B$8,9)) | M7: =SUMIFS(JOURNAL!$I$5:$I$504,JOURNAL!$C$5:$C$504,$A7,JOURNAL!$A$5:$A$504,">="&DATE(YEAR(SETUP!$B$8),MONTH(SETUP!$B$8)+10,1),JOURNAL!$A$5:$A$504,"<="&EOMONTH(SETUP!$B$8,10))-SUMIFS(JOURNAL!$J$5:$J$504,JOURNAL!$C$5:$C$504,$A7,JOURNAL!$A$5:$A$504,">="&DATE(YEAR(SETUP!$B$8),MONTH(SETUP!$B$8)+10,1),JOURNAL!$A$5:$A$504,"<="&EOMONTH(SETUP!$B$8,10)) | N7: =SUMIFS(JOURNAL!$I$5:$I$504,JOURNAL!$C$5:$C$504,$A7,JOURNAL!$A$5:$A$504,">="&DATE(YEAR(SETUP!$B$8),MONTH(SETUP!$B$8)+11,1),JOURNAL!$A$5:$A$504,"<="&EOMONTH(SETUP!$B$8,11))-SUMIFS(JOURNAL!$J$5:$J$504,JOURNAL!$C$5:$C$504,$A7,JOURNAL!$A$5:$A$504,">="&DATE(YEAR(SETUP!$B$8),MONTH(SETUP!$B$8)+11,1),JOURNAL!$A$5:$A$504,"<="&EOMONTH(SETUP!$B$8,11)) | O7: =SUM(C7:N7)
A8: 1100 | B8: Trade receivables | C8: =SUMIFS(JOURNAL!$I$5:$I$504,JOURNAL!$C$5:$C$504,$A8,JOURNAL!$A$5:$A$504,">="&DATE(YEAR(SETUP!$B$8),MONTH(SETUP!$B$8)+0,1),JOURNAL!$A$5:$A$504,"<="&EOMONTH(SETUP!$B$8,0))-SUMIFS(JOURNAL!$J$5:$J$504,JOURNAL!$C$5:$C$504,$A8,JOURNAL!$A$5:$A$504,">="&DATE(YEAR(SETUP!$B$8),MONTH(SETUP!$B$8)+0,1),JOURNAL!$A$5:$A$504,"<="&EOMONTH(SETUP!$B$8,0)) | D8: =SUMIFS(JOURNAL!$I$5:$I$504,JOURNAL!$C$5:$C$504,$A8,JOURNAL!$A$5:$A$504,">="&DATE(YEAR(SETUP!$B$8),MONTH(SETUP!$B$8)+1,1),JOURNAL!$A$5:$A$504,"<="&EOMONTH(SETUP!$B$8,1))-SUMIFS(JOURNAL!$J$5:$J$504,JOURNAL!$C$5:$C$504,$A8,JOURNAL!$A$5:$A$504,">="&DATE(YEAR(SETUP!$B$8),MONTH(SETUP!$B$8)+1,1),JOURNAL!$A$5:$A$504,"<="&EOMONTH(SETUP!$B$8,1)) | E8: =SUMIFS(JOURNAL!$I$5:$I$504,JOURNAL!$C$5:$C$504,$A8,JOURNAL!$A$5:$A$504,">="&DATE(YEAR(SETUP!$B$8),MONTH(SETUP!$B$8)+2,1),JOURNAL!$A$5:$A$504,"<="&EOMONTH(SETUP!$B$8,2))-SUMIFS(JOURNAL!$J$5:$J$504,JOURNAL!$C$5:$C$504,$A8,JOURNAL!$A$5:$A$504,">="&DATE(YEAR(SETUP!$B$8),MONTH(SETUP!$B$8)+2,1),JOURNAL!$A$5:$A$504,"<="&EOMONTH(SETUP!$B$8,2)) | F8: =SUMIFS(JOURNAL!$I$5:$I$504,JOURNAL!$C$5:$C$504,$A8,JOURNAL!$A$5:$A$504,">="&DATE(YEAR(SETUP!$B$8),MONTH(SETUP!$B$8)+3,1),JOURNAL!$A$5:$A$504,"<="&EOMONTH(SETUP!$B$8,3))-SUMIFS(JOURNAL!$J$5:$J$504,JOURNAL!$C$5:$C$504,$A8,JOURNAL!$A$5:$A$504,">="&DATE(YEAR(SETUP!$B$8),MONTH(SETUP!$B$8)+3,1),JOURNAL!$A$5:$A$504,"<="&EOMONTH(SETUP!$B$8,3)) | G8: =SUMIFS(JOURNAL!$I$5:$I$504,JOURNAL!$C$5:$C$504,$A8,JOURNAL!$A$5:$A$504,">="&DATE(YEAR(SETUP!$B$8),MONTH(SETUP!$B$8)+4,1),JOURNAL!$A$5:$A$504,"<="&EOMONTH(SETUP!$B$8,4))-SUMIFS(JOURNAL!$J$5:$J$504,JOURNAL!$C$5:$C$504,$A8,JOURNAL!$A$5:$A$504,">="&DATE(YEAR(SETUP!$B$8),MONTH(SETUP!$B$8)+4,1),JOURNAL!$A$5:$A$504,"<="&EOMONTH(SETUP!$B$8,4)) | H8: =SUMIFS(JOURNAL!$I$5:$I$504,JOURNAL!$C$5:$C$504,$A8,JOURNAL!$A$5:$A$504,">="&DATE(YEAR(SETUP!$B$8),MONTH(SETUP!$B$8)+5,1),JOURNAL!$A$5:$A$504,"<="&EOMONTH(SETUP!$B$8,5))-SUMIFS(JOURNAL!$J$5:$J$504,JOURNAL!$C$5:$C$504,$A8,JOURNAL!$A$5:$A$504,">="&DATE(YEAR(SETUP!$B$8),MONTH(SETUP!$B$8)+5,1),JOURNAL!$A$5:$A$504,"<="&EOMONTH(SETUP!$B$8,5)) | I8: =SUMIFS(JOURNAL!$I$5:$I$504,JOURNAL!$C$5:$C$504,$A8,JOURNAL!$A$5:$A$504,">="&DATE(YEAR(SETUP!$B$8),MONTH(SETUP!$B$8)+6,1),JOURNAL!$A$5:$A$504,"<="&EOMONTH(SETUP!$B$8,6))-SUMIFS(JOURNAL!$J$5:$J$504,JOURNAL!$C$5:$C$504,$A8,JOURNAL!$A$5:$A$504,">="&DATE(YEAR(SETUP!$B$8),MONTH(SETUP!$B$8)+6,1),JOURNAL!$A$5:$A$504,"<="&EOMONTH(SETUP!$B$8,6)) | J8: =SUMIFS(JOURNAL!$I$5:$I$504,JOURNAL!$C$5:$C$504,$A8,JOURNAL!$A$5:$A$504,">="&DATE(YEAR(SETUP!$B$8),MONTH(SETUP!$B$8)+7,1),JOURNAL!$A$5:$A$504,"<="&EOMONTH(SETUP!$B$8,7))-SUMIFS(JOURNAL!$J$5:$J$504,JOURNAL!$C$5:$C$504,$A8,JOURNAL!$A$5:$A$504,">="&DATE(YEAR(SETUP!$B$8),MONTH(SETUP!$B$8)+7,1),JOURNAL!$A$5:$A$504,"<="&EOMONTH(SETUP!$B$8,7)) | K8: =SUMIFS(JOURNAL!$I$5:$I$504,JOURNAL!$C$5:$C$504,$A8,JOURNAL!$A$5:$A$504,">="&DATE(YEAR(SETUP!$B$8),MONTH(SETUP!$B$8)+8,1),JOURNAL!$A$5:$A$504,"<="&EOMONTH(SETUP!$B$8,8))-SUMIFS(JOURNAL!$J$5:$J$504,JOURNAL!$C$5:$C$504,$A8,JOURNAL!$A$5:$A$504,">="&DATE(YEAR(SETUP!$B$8),MONTH(SETUP!$B$8)+8,1),JOURNAL!$A$5:$A$504,"<="&EOMONTH(SETUP!$B$8,8)) | L8: =SUMIFS(JOURNAL!$I$5:$I$504,JOURNAL!$C$5:$C$504,$A8,JOURNAL!$A$5:$A$504,">="&DATE(YEAR(SETUP!$B$8),MONTH(SETUP!$B$8)+9,1),JOURNAL!$A$5:$A$504,"<="&EOMONTH(SETUP!$B$8,9))-SUMIFS(JOURNAL!$J$5:$J$504,JOURNAL!$C$5:$C$504,$A8,JOURNAL!$A$5:$A$504,">="&DATE(YEAR(SETUP!$B$8),MONTH(SETUP!$B$8)+9,1),JOURNAL!$A$5:$A$504,"<="&EOMONTH(SETUP!$B$8,9)) | M8: =SUMIFS(JOURNAL!$I$5:$I$504,JOURNAL!$C$5:$C$504,$A8,JOURNAL!$A$5:$A$504,">="&DATE(YEAR(SETUP!$B$8),MONTH(SETUP!$B$8)+10,1),JOURNAL!$A$5:$A$504,"<="&EOMONTH(SETUP!$B$8,10))-SUMIFS(JOURNAL!$J$5:$J$504,JOURNAL!$C$5:$C$504,$A8,JOURNAL!$A$5:$A$504,">="&DATE(YEAR(SETUP!$B$8),MONTH(SETUP!$B$8)+10,1),JOURNAL!$A$5:$A$504,"<="&EOMONTH(SETUP!$B$8,10)) | N8: =SUMIFS(JOURNAL!$I$5:$I$504,JOURNAL!$C$5:$C$504,$A8,JOURNAL!$A$5:$A$504,">="&DATE(YEAR(SETUP!$B$8),MONTH(SETUP!$B$8)+11,1),JOURNAL!$A$5:$A$504,"<="&EOMONTH(SETUP!$B$8,11))-SUMIFS(JOURNAL!$J$5:$J$504,JOURNAL!$C$5:$C$504,$A8,JOURNAL!$A$5:$A$504,">="&DATE(YEAR(SETUP!$B$8),MONTH(SETUP!$B$8)+11,1),JOURNAL!$A$5:$A$504,"<="&EOMONTH(SETUP!$B$8,11)) | O8: =SUM(C8:N8)
A9: 1200 | B9: Inventory — preforms and bottles | C9: =SUMIFS(JOURNAL!$I$5:$I$504,JOURNAL!$C$5:$C$504,$A9,JOURNAL!$A$5:$A$504,">="&DATE(YEAR(SETUP!$B$8),MONTH(SETUP!$B$8)+0,1),JOURNAL!$A$5:$A$504,"<="&EOMONTH(SETUP!$B$8,0))-SUMIFS(JOURNAL!$J$5:$J$504,JOURNAL!$C$5:$C$504,$A9,JOURNAL!$A$5:$A$504,">="&DATE(YEAR(SETUP!$B$8),MONTH(SETUP!$B$8)+0,1),JOURNAL!$A$5:$A$504,"<="&EOMONTH(SETUP!$B$8,0)) | D9: =SUMIFS(JOURNAL!$I$5:$I$504,JOURNAL!$C$5:$C$504,$A9,JOURNAL!$A$5:$A$504,">="&DATE(YEAR(SETUP!$B$8),MONTH(SETUP!$B$8)+1,1),JOURNAL!$A$5:$A$504,"<="&EOMONTH(SETUP!$B$8,1))-SUMIFS(JOURNAL!$J$5:$J$504,JOURNAL!$C$5:$C$504,$A9,JOURNAL!$A$5:$A$504,">="&DATE(YEAR(SETUP!$B$8),MONTH(SETUP!$B$8)+1,1),JOURNAL!$A$5:$A$504,"<="&EOMONTH(SETUP!$B$8,1)) | E9: =SUMIFS(JOURNAL!$I$5:$I$504,JOURNAL!$C$5:$C$504,$A9,JOURNAL!$A$5:$A$504,">="&DATE(YEAR(SETUP!$B$8),MONTH(SETUP!$B$8)+2,1),JOURNAL!$A$5:$A$504,"<="&EOMONTH(SETUP!$B$8,2))-SUMIFS(JOURNAL!$J$5:$J$504,JOURNAL!$C$5:$C$504,$A9,JOURNAL!$A$5:$A$504,">="&DATE(YEAR(SETUP!$B$8),MONTH(SETUP!$B$8)+2,1),JOURNAL!$A$5:$A$504,"<="&EOMONTH(SETUP!$B$8,2)) | F9: =SUMIFS(JOURNAL!$I$5:$I$504,JOURNAL!$C$5:$C$504,$A9,JOURNAL!$A$5:$A$504,">="&DATE(YEAR(SETUP!$B$8),MONTH(SETUP!$B$8)+3,1),JOURNAL!$A$5:$A$504,"<="&EOMONTH(SETUP!$B$8,3))-SUMIFS(JOURNAL!$J$5:$J$504,JOURNAL!$C$5:$C$504,$A9,JOURNAL!$A$5:$A$504,">="&DATE(YEAR(SETUP!$B$8),MONTH(SETUP!$B$8)+3,1),JOURNAL!$A$5:$A$504,"<="&EOMONTH(SETUP!$B$8,3)) | G9: =SUMIFS(JOURNAL!$I$5:$I$504,JOURNAL!$C$5:$C$504,$A9,JOURNAL!$A$5:$A$504,">="&DATE(YEAR(SETUP!$B$8),MONTH(SETUP!$B$8)+4,1),JOURNAL!$A$5:$A$504,"<="&EOMONTH(SETUP!$B$8,4))-SUMIFS(JOURNAL!$J$5:$J$504,JOURNAL!$C$5:$C$504,$A9,JOURNAL!$A$5:$A$504,">="&DATE(YEAR(SETUP!$B$8),MONTH(SETUP!$B$8)+4,1),JOURNAL!$A$5:$A$504,"<="&EOMONTH(SETUP!$B$8,4)) | H9: =SUMIFS(JOURNAL!$I$5:$I$504,JOURNAL!$C$5:$C$504,$A9,JOURNAL!$A$5:$A$504,">="&DATE(YEAR(SETUP!$B$8),MONTH(SETUP!$B$8)+5,1),JOURNAL!$A$5:$A$504,"<="&EOMONTH(SETUP!$B$8,5))-SUMIFS(JOURNAL!$J$5:$J$504,JOURNAL!$C$5:$C$504,$A9,JOURNAL!$A$5:$A$504,">="&DATE(YEAR(SETUP!$B$8),MONTH(SETUP!$B$8)+5,1),JOURNAL!$A$5:$A$504,"<="&EOMONTH(SETUP!$B$8,5)) | I9: =SUMIFS(JOURNAL!$I$5:$I$504,JOURNAL!$C$5:$C$504,$A9,JOURNAL!$A$5:$A$504,">="&DATE(YEAR(SETUP!$B$8),MONTH(SETUP!$B$8)+6,1),JOURNAL!$A$5:$A$504,"<="&EOMONTH(SETUP!$B$8,6))-SUMIFS(JOURNAL!$J$5:$J$504,JOURNAL!$C$5:$C$504,$A9,JOURNAL!$A$5:$A$504,">="&DATE(YEAR(SETUP!$B$8),MONTH(SETUP!$B$8)+6,1),JOURNAL!$A$5:$A$504,"<="&EOMONTH(SETUP!$B$8,6)) | J9: =SUMIFS(JOURNAL!$I$5:$I$504,JOURNAL!$C$5:$C$504,$A9,JOURNAL!$A$5:$A$504,">="&DATE(YEAR(SETUP!$B$8),MONTH(SETUP!$B$8)+7,1),JOURNAL!$A$5:$A$504,"<="&EOMONTH(SETUP!$B$8,7))-SUMIFS(JOURNAL!$J$5:$J$504,JOURNAL!$C$5:$C$504,$A9,JOURNAL!$A$5:$A$504,">="&DATE(YEAR(SETUP!$B$8),MONTH(SETUP!$B$8)+7,1),JOURNAL!$A$5:$A$504,"<="&EOMONTH(SETUP!$B$8,7)) | K9: =SUMIFS(JOURNAL!$I$5:$I$504,JOURNAL!$C$5:$C$504,$A9,JOURNAL!$A$5:$A$504,">="&DATE(YEAR(SETUP!$B$8),MONTH(SETUP!$B$8)+8,1),JOURNAL!$A$5:$A$504,"<="&EOMONTH(SETUP!$B$8,8))-SUMIFS(JOURNAL!$J$5:$J$504,JOURNAL!$C$5:$C$504,$A9,JOURNAL!$A$5:$A$504,">="&DATE(YEAR(SETUP!$B$8),MONTH(SETUP!$B$8)+8,1),JOURNAL!$A$5:$A$504,"<="&EOMONTH(SETUP!$B$8,8)) | L9: =SUMIFS(JOURNAL!$I$5:$I$504,JOURNAL!$C$5:$C$504,$A9,JOURNAL!$A$5:$A$504,">="&DATE(YEAR(SETUP!$B$8),MONTH(SETUP!$B$8)+9,1),JOURNAL!$A$5:$A$504,"<="&EOMONTH(SETUP!$B$8,9))-SUMIFS(JOURNAL!$J$5:$J$504,JOURNAL!$C$5:$C$504,$A9,JOURNAL!$A$5:$A$504,">="&DATE(YEAR(SETUP!$B$8),MONTH(SETUP!$B$8)+9,1),JOURNAL!$A$5:$A$504,"<="&EOMONTH(SETUP!$B$8,9)) | M9: =SUMIFS(JOURNAL!$I$5:$I$504,JOURNAL!$C$5:$C$504,$A9,JOURNAL!$A$5:$A$504,">="&DATE(YEAR(SETUP!$B$8),MONTH(SETUP!$B$8)+10,1),JOURNAL!$A$5:$A$504,"<="&EOMONTH(SETUP!$B$8,10))-SUMIFS(JOURNAL!$J$5:$J$504,JOURNAL!$C$5:$C$504,$A9,JOURNAL!$A$5:$A$504,">="&DATE(YEAR(SETUP!$B$8),MONTH(SETUP!$B$8)+10,1),JOURNAL!$A$5:$A$504,"<="&EOMONTH(SETUP!$B$8,10)) | N9: =SUMIFS(JOURNAL!$I$5:$I$504,JOURNAL!$C$5:$C$504,$A9,JOURNAL!$A$5:$A$504,">="&DATE(YEAR(SETUP!$B$8),MONTH(SETUP!$B$8)+11,1),JOURNAL!$A$5:$A$504,"<="&EOMONTH(SETUP!$B$8,11))-SUMIFS(JOURNAL!$J$5:$J$504,JOURNAL!$C$5:$C$504,$A9,JOURNAL!$A$5:$A$504,">="&DATE(YEAR(SETUP!$B$8),MONTH(SETUP!$B$8)+11,1),JOURNAL!$A$5:$A$504,"<="&EOMONTH(SETUP!$B$8,11)) | O9: =SUM(C9:N9)
A10: 1210 | B10: Inventory — caps and labels | C10: =SUMIFS(JOURNAL!$I$5:$I$504,JOURNAL!$C$5:$C$504,$A10,JOURNAL!$A$5:$A$504,">="&DATE(YEAR(SETUP!$B$8),MONTH(SETUP!$B$8)+0,1),JOURNAL!$A$5:$A$504,"<="&EOMONTH(SETUP!$B$8,0))-SUMIFS(JOURNAL!$J$5:$J$504,JOURNAL!$C$5:$C$504,$A10,JOURNAL!$A$5:$A$504,">="&DATE(YEAR(SETUP!$B$8),MONTH(SETUP!$B$8)+0,1),JOURNAL!$A$5:$A$504,"<="&EOMONTH(SETUP!$B$8,0)) | D10: =SUMIFS(JOURNAL!$I$5:$I$504,JOURNAL!$C$5:$C$504,$A10,JOURNAL!$A$5:$A$504,">="&DATE(YEAR(SETUP!$B$8),MONTH(SETUP!$B$8)+1,1),JOURNAL!$A$5:$A$504,"<="&EOMONTH(SETUP!$B$8,1))-SUMIFS(JOURNAL!$J$5:$J$504,JOURNAL!$C$5:$C$504,$A10,JOURNAL!$A$5:$A$504,">="&DATE(YEAR(SETUP!$B$8),MONTH(SETUP!$B$8)+1,1),JOURNAL!$A$5:$A$504,"<="&EOMONTH(SETUP!$B$8,1)) | E10: =SUMIFS(JOURNAL!$I$5:$I$504,JOURNAL!$C$5:$C$504,$A10,JOURNAL!$A$5:$A$504,">="&DATE(YEAR(SETUP!$B$8),MONTH(SETUP!$B$8)+2,1),JOURNAL!$A$5:$A$504,"<="&EOMONTH(SETUP!$B$8,2))-SUMIFS(JOURNAL!$J$5:$J$504,JOURNAL!$C$5:$C$504,$A10,JOURNAL!$A$5:$A$504,">="&DATE(YEAR(SETUP!$B$8),MONTH(SETUP!$B$8)+2,1),JOURNAL!$A$5:$A$504,"<="&EOMONTH(SETUP!$B$8,2)) | F10: =SUMIFS(JOURNAL!$I$5:$I$504,JOURNAL!$C$5:$C$504,$A10,JOURNAL!$A$5:$A$504,">="&DATE(YEAR(SETUP!$B$8),MONTH(SETUP!$B$8)+3,1),JOURNAL!$A$5:$A$504,"<="&EOMONTH(SETUP!$B$8,3))-SUMIFS(JOURNAL!$J$5:$J$504,JOURNAL!$C$5:$C$504,$A10,JOURNAL!$A$5:$A$504,">="&DATE(YEAR(SETUP!$B$8),MONTH(SETUP!$B$8)+3,1),JOURNAL!$A$5:$A$504,"<="&EOMONTH(SETUP!$B$8,3)) | G10: =SUMIFS(JOURNAL!$I$5:$I$504,JOURNAL!$C$5:$C$504,$A10,JOURNAL!$A$5:$A$504,">="&DATE(YEAR(SETUP!$B$8),MONTH(SETUP!$B$8)+4,1),JOURNAL!$A$5:$A$504,"<="&EOMONTH(SETUP!$B$8,4))-SUMIFS(JOURNAL!$J$5:$J$504,JOURNAL!$C$5:$C$504,$A10,JOURNAL!$A$5:$A$504,">="&DATE(YEAR(SETUP!$B$8),MONTH(SETUP!$B$8)+4,1),JOURNAL!$A$5:$A$504,"<="&EOMONTH(SETUP!$B$8,4)) | H10: =SUMIFS(JOURNAL!$I$5:$I$504,JOURNAL!$C$5:$C$504,$A10,JOURNAL!$A$5:$A$504,">="&DATE(YEAR(SETUP!$B$8),MONTH(SETUP!$B$8)+5,1),JOURNAL!$A$5:$A$504,"<="&EOMONTH(SETUP!$B$8,5))-SUMIFS(JOURNAL!$J$5:$J$504,JOURNAL!$C$5:$C$504,$A10,JOURNAL!$A$5:$A$504,">="&DATE(YEAR(SETUP!$B$8),MONTH(SETUP!$B$8)+5,1),JOURNAL!$A$5:$A$504,"<="&EOMONTH(SETUP!$B$8,5)) | I10: =SUMIFS(JOURNAL!$I$5:$I$504,JOURNAL!$C$5:$C$504,$A10,JOURNAL!$A$5:$A$504,">="&DATE(YEAR(SETUP!$B$8),MONTH(SETUP!$B$8)+6,1),JOURNAL!$A$5:$A$504,"<="&EOMONTH(SETUP!$B$8,6))-SUMIFS(JOURNAL!$J$5:$J$504,JOURNAL!$C$5:$C$504,$A10,JOURNAL!$A$5:$A$504,">="&DATE(YEAR(SETUP!$B$8),MONTH(SETUP!$B$8)+6,1),JOURNAL!$A$5:$A$504,"<="&EOMONTH(SETUP!$B$8,6)) | J10: =SUMIFS(JOURNAL!$I$5:$I$504,JOURNAL!$C$5:$C$504,$A10,JOURNAL!$A$5:$A$504,">="&DATE(YEAR(SETUP!$B$8),MONTH(SETUP!$B$8)+7,1),JOURNAL!$A$5:$A$504,"<="&EOMONTH(SETUP!$B$8,7))-SUMIFS(JOURNAL!$J$5:$J$504,JOURNAL!$C$5:$C$504,$A10,JOURNAL!$A$5:$A$504,">="&DATE(YEAR(SETUP!$B$8),MONTH(SETUP!$B$8)+7,1),JOURNAL!$A$5:$A$504,"<="&EOMONTH(SETUP!$B$8,7)) | K10: =SUMIFS(JOURNAL!$I$5:$I$504,JOURNAL!$C$5:$C$504,$A10,JOURNAL!$A$5:$A$504,">="&DATE(YEAR(SETUP!$B$8),MONTH(SETUP!$B$8)+8,1),JOURNAL!$A$5:$A$504,"<="&EOMONTH(SETUP!$B$8,8))-SUMIFS(JOURNAL!$J$5:$J$504,JOURNAL!$C$5:$C$504,$A10,JOURNAL!$A$5:$A$504,">="&DATE(YEAR(SETUP!$B$8),MONTH(SETUP!$B$8)+8,1),JOURNAL!$A$5:$A$504,"<="&EOMONTH(SETUP!$B$8,8)) | L10: =SUMIFS(JOURNAL!$I$5:$I$504,JOURNAL!$C$5:$C$504,$A10,JOURNAL!$A$5:$A$504,">="&DATE(YEAR(SETUP!$B$8),MONTH(SETUP!$B$8)+9,1),JOURNAL!$A$5:$A$504,"<="&EOMONTH(SETUP!$B$8,9))-SUMIFS(JOURNAL!$J$5:$J$504,JOURNAL!$C$5:$C$504,$A10,JOURNAL!$A$5:$A$504,">="&DATE(YEAR(SETUP!$B$8),MONTH(SETUP!$B$8)+9,1),JOURNAL!$A$5:$A$504,"<="&EOMONTH(SETUP!$B$8,9)) | M10: =SUMIFS(JOURNAL!$I$5:$I$504,JOURNAL!$C$5:$C$504,$A10,JOURNAL!$A$5:$A$504,">="&DATE(YEAR(SETUP!$B$8),MONTH(SETUP!$B$8)+10,1),JOURNAL!$A$5:$A$504,"<="&EOMONTH(SETUP!$B$8,10))-SUMIFS(JOURNAL!$J$5:$J$504,JOURNAL!$C$5:$C$504,$A10,JOURNAL!$A$5:$A$504,">="&DATE(YEAR(SETUP!$B$8),MONTH(SETUP!$B$8)+10,1),JOURNAL!$A$5:$A$504,"<="&EOMONTH(SETUP!$B$8,10)) | N10: =SUMIFS(JOURNAL!$I$5:$I$504,JOURNAL!$C$5:$C$504,$A10,JOURNAL!$A$5:$A$504,">="&DATE(YEAR(SETUP!$B$8),MONTH(SETUP!$B$8)+11,1),JOURNAL!$A$5:$A$504,"<="&EOMONTH(SETUP!$B$8,11))-SUMIFS(JOURNAL!$J$5:$J$504,JOURNAL!$C$5:$C$504,$A10,JOURNAL!$A$5:$A$504,">="&DATE(YEAR(SETUP!$B$8),MONTH(SETUP!$B$8)+11,1),JOURNAL!$A$5:$A$504,"<="&EOMONTH(SETUP!$B$8,11)) | O10: =SUM(C10:N10)
A11: 1220 | B11: Inventory — jars held for issue | C11: =SUMIFS(JOURNAL!$I$5:$I$504,JOURNAL!$C$5:$C$504,$A11,JOURNAL!$A$5:$A$504,">="&DATE(YEAR(SETUP!$B$8),MONTH(SETUP!$B$8)+0,1),JOURNAL!$A$5:$A$504,"<="&EOMONTH(SETUP!$B$8,0))-SUMIFS(JOURNAL!$J$5:$J$504,JOURNAL!$C$5:$C$504,$A11,JOURNAL!$A$5:$A$504,">="&DATE(YEAR(SETUP!$B$8),MONTH(SETUP!$B$8)+0,1),JOURNAL!$A$5:$A$504,"<="&EOMONTH(SETUP!$B$8,0)) | D11: =SUMIFS(JOURNAL!$I$5:$I$504,JOURNAL!$C$5:$C$504,$A11,JOURNAL!$A$5:$A$504,">="&DATE(YEAR(SETUP!$B$8),MONTH(SETUP!$B$8)+1,1),JOURNAL!$A$5:$A$504,"<="&EOMONTH(SETUP!$B$8,1))-SUMIFS(JOURNAL!$J$5:$J$504,JOURNAL!$C$5:$C$504,$A11,JOURNAL!$A$5:$A$504,">="&DATE(YEAR(SETUP!$B$8),MONTH(SETUP!$B$8)+1,1),JOURNAL!$A$5:$A$504,"<="&EOMONTH(SETUP!$B$8,1)) | E11: =SUMIFS(JOURNAL!$I$5:$I$504,JOURNAL!$C$5:$C$504,$A11,JOURNAL!$A$5:$A$504,">="&DATE(YEAR(SETUP!$B$8),MONTH(SETUP!$B$8)+2,1),JOURNAL!$A$5:$A$504,"<="&EOMONTH(SETUP!$B$8,2))-SUMIFS(JOURNAL!$J$5:$J$504,JOURNAL!$C$5:$C$504,$A11,JOURNAL!$A$5:$A$504,">="&DATE(YEAR(SETUP!$B$8),MONTH(SETUP!$B$8)+2,1),JOURNAL!$A$5:$A$504,"<="&EOMONTH(SETUP!$B$8,2)) | F11: =SUMIFS(JOURNAL!$I$5:$I$504,JOURNAL!$C$5:$C$504,$A11,JOURNAL!$A$5:$A$504,">="&DATE(YEAR(SETUP!$B$8),MONTH(SETUP!$B$8)+3,1),JOURNAL!$A$5:$A$504,"<="&EOMONTH(SETUP!$B$8,3))-SUMIFS(JOURNAL!$J$5:$J$504,JOURNAL!$C$5:$C$504,$A11,JOURNAL!$A$5:$A$504,">="&DATE(YEAR(SETUP!$B$8),MONTH(SETUP!$B$8)+3,1),JOURNAL!$A$5:$A$504,"<="&EOMONTH(SETUP!$B$8,3)) | G11: =SUMIFS(JOURNAL!$I$5:$I$504,JOURNAL!$C$5:$C$504,$A11,JOURNAL!$A$5:$A$504,">="&DATE(YEAR(SETUP!$B$8),MONTH(SETUP!$B$8)+4,1),JOURNAL!$A$5:$A$504,"<="&EOMONTH(SETUP!$B$8,4))-SUMIFS(JOURNAL!$J$5:$J$504,JOURNAL!$C$5:$C$504,$A11,JOURNAL!$A$5:$A$504,">="&DATE(YEAR(SETUP!$B$8),MONTH(SETUP!$B$8)+4,1),JOURNAL!$A$5:$A$504,"<="&EOMONTH(SETUP!$B$8,4)) | H11: =SUMIFS(JOURNAL!$I$5:$I$504,JOURNAL!$C$5:$C$504,$A11,JOURNAL!$A$5:$A$504,">="&DATE(YEAR(SETUP!$B$8),MONTH(SETUP!$B$8)+5,1),JOURNAL!$A$5:$A$504,"<="&EOMONTH(SETUP!$B$8,5))-SUMIFS(JOURNAL!$J$5:$J$504,JOURNAL!$C$5:$C$504,$A11,JOURNAL!$A$5:$A$504,">="&DATE(YEAR(SETUP!$B$8),MONTH(SETUP!$B$8)+5,1),JOURNAL!$A$5:$A$504,"<="&EOMONTH(SETUP!$B$8,5)) | I11: =SUMIFS(JOURNAL!$I$5:$I$504,JOURNAL!$C$5:$C$504,$A11,JOURNAL!$A$5:$A$504,">="&DATE(YEAR(SETUP!$B$8),MONTH(SETUP!$B$8)+6,1),JOURNAL!$A$5:$A$504,"<="&EOMONTH(SETUP!$B$8,6))-SUMIFS(JOURNAL!$J$5:$J$504,JOURNAL!$C$5:$C$504,$A11,JOURNAL!$A$5:$A$504,">="&DATE(YEAR(SETUP!$B$8),MONTH(SETUP!$B$8)+6,1),JOURNAL!$A$5:$A$504,"<="&EOMONTH(SETUP!$B$8,6)) | J11: =SUMIFS(JOURNAL!$I$5:$I$504,JOURNAL!$C$5:$C$504,$A11,JOURNAL!$A$5:$A$504,">="&DATE(YEAR(SETUP!$B$8),MONTH(SETUP!$B$8)+7,1),JOURNAL!$A$5:$A$504,"<="&EOMONTH(SETUP!$B$8,7))-SUMIFS(JOURNAL!$J$5:$J$504,JOURNAL!$C$5:$C$504,$A11,JOURNAL!$A$5:$A$504,">="&DATE(YEAR(SETUP!$B$8),MONTH(SETUP!$B$8)+7,1),JOURNAL!$A$5:$A$504,"<="&EOMONTH(SETUP!$B$8,7)) | K11: =SUMIFS(JOURNAL!$I$5:$I$504,JOURNAL!$C$5:$C$504,$A11,JOURNAL!$A$5:$A$504,">="&DATE(YEAR(SETUP!$B$8),MONTH(SETUP!$B$8)+8,1),JOURNAL!$A$5:$A$504,"<="&EOMONTH(SETUP!$B$8,8))-SUMIFS(JOURNAL!$J$5:$J$504,JOURNAL!$C$5:$C$504,$A11,JOURNAL!$A$5:$A$504,">="&DATE(YEAR(SETUP!$B$8),MONTH(SETUP!$B$8)+8,1),JOURNAL!$A$5:$A$504,"<="&EOMONTH(SETUP!$B$8,8)) | L11: =SUMIFS(JOURNAL!$I$5:$I$504,JOURNAL!$C$5:$C$504,$A11,JOURNAL!$A$5:$A$504,">="&DATE(YEAR(SETUP!$B$8),MONTH(SETUP!$B$8)+9,1),JOURNAL!$A$5:$A$504,"<="&EOMONTH(SETUP!$B$8,9))-SUMIFS(JOURNAL!$J$5:$J$504,JOURNAL!$C$5:$C$504,$A11,JOURNAL!$A$5:$A$504,">="&DATE(YEAR(SETUP!$B$8),MONTH(SETUP!$B$8)+9,1),JOURNAL!$A$5:$A$504,"<="&EOMONTH(SETUP!$B$8,9)) | M11: =SUMIFS(JOURNAL!$I$5:$I$504,JOURNAL!$C$5:$C$504,$A11,JOURNAL!$A$5:$A$504,">="&DATE(YEAR(SETUP!$B$8),MONTH(SETUP!$B$8)+10,1),JOURNAL!$A$5:$A$504,"<="&EOMONTH(SETUP!$B$8,10))-SUMIFS(JOURNAL!$J$5:$J$504,JOURNAL!$C$5:$C$504,$A11,JOURNAL!$A$5:$A$504,">="&DATE(YEAR(SETUP!$B$8),MONTH(SETUP!$B$8)+10,1),JOURNAL!$A$5:$A$504,"<="&EOMONTH(SETUP!$B$8,10)) | N11: =SUMIFS(JOURNAL!$I$5:$I$504,JOURNAL!$C$5:$C$504,$A11,JOURNAL!$A$5:$A$504,">="&DATE(YEAR(SETUP!$B$8),MONTH(SETUP!$B$8)+11,1),JOURNAL!$A$5:$A$504,"<="&EOMONTH(SETUP!$B$8,11))-SUMIFS(JOURNAL!$J$5:$J$504,JOURNAL!$C$5:$C$504,$A11,JOURNAL!$A$5:$A$504,">="&DATE(YEAR(SETUP!$B$8),MONTH(SETUP!$B$8)+11,1),JOURNAL!$A$5:$A$504,"<="&EOMONTH(SETUP!$B$8,11)) | O11: =SUM(C11:N11)
A12: 1230 | B12: Inventory — treatment consumables | C12: =SUMIFS(JOURNAL!$I$5:$I$504,JOURNAL!$C$5:$C$504,$A12,JOURNAL!$A$5:$A$504,">="&DATE(YEAR(SETUP!$B$8),MONTH(SETUP!$B$8)+0,1),JOURNAL!$A$5:$A$504,"<="&EOMONTH(SETUP!$B$8,0))-SUMIFS(JOURNAL!$J$5:$J$504,JOURNAL!$C$5:$C$504,$A12,JOURNAL!$A$5:$A$504,">="&DATE(YEAR(SETUP!$B$8),MONTH(SETUP!$B$8)+0,1),JOURNAL!$A$5:$A$504,"<="&EOMONTH(SETUP!$B$8,0)) | D12: =SUMIFS(JOURNAL!$I$5:$I$504,JOURNAL!$C$5:$C$504,$A12,JOURNAL!$A$5:$A$504,">="&DATE(YEAR(SETUP!$B$8),MONTH(SETUP!$B$8)+1,1),JOURNAL!$A$5:$A$504,"<="&EOMONTH(SETUP!$B$8,1))-SUMIFS(JOURNAL!$J$5:$J$504,JOURNAL!$C$5:$C$504,$A12,JOURNAL!$A$5:$A$504,">="&DATE(YEAR(SETUP!$B$8),MONTH(SETUP!$B$8)+1,1),JOURNAL!$A$5:$A$504,"<="&EOMONTH(SETUP!$B$8,1)) | E12: =SUMIFS(JOURNAL!$I$5:$I$504,JOURNAL!$C$5:$C$504,$A12,JOURNAL!$A$5:$A$504,">="&DATE(YEAR(SETUP!$B$8),MONTH(SETUP!$B$8)+2,1),JOURNAL!$A$5:$A$504,"<="&EOMONTH(SETUP!$B$8,2))-SUMIFS(JOURNAL!$J$5:$J$504,JOURNAL!$C$5:$C$504,$A12,JOURNAL!$A$5:$A$504,">="&DATE(YEAR(SETUP!$B$8),MONTH(SETUP!$B$8)+2,1),JOURNAL!$A$5:$A$504,"<="&EOMONTH(SETUP!$B$8,2)) | F12: =SUMIFS(JOURNAL!$I$5:$I$504,JOURNAL!$C$5:$C$504,$A12,JOURNAL!$A$5:$A$504,">="&DATE(YEAR(SETUP!$B$8),MONTH(SETUP!$B$8)+3,1),JOURNAL!$A$5:$A$504,"<="&EOMONTH(SETUP!$B$8,3))-SUMIFS(JOURNAL!$J$5:$J$504,JOURNAL!$C$5:$C$504,$A12,JOURNAL!$A$5:$A$504,">="&DATE(YEAR(SETUP!$B$8),MONTH(SETUP!$B$8)+3,1),JOURNAL!$A$5:$A$504,"<="&EOMONTH(SETUP!$B$8,3)) | G12: =SUMIFS(JOURNAL!$I$5:$I$504,JOURNAL!$C$5:$C$504,$A12,JOURNAL!$A$5:$A$504,">="&DATE(YEAR(SETUP!$B$8),MONTH(SETUP!$B$8)+4,1),JOURNAL!$A$5:$A$504,"<="&EOMONTH(SETUP!$B$8,4))-SUMIFS(JOURNAL!$J$5:$J$504,JOURNAL!$C$5:$C$504,$A12,JOURNAL!$A$5:$A$504,">="&DATE(YEAR(SETUP!$B$8),MONTH(SETUP!$B$8)+4,1),JOURNAL!$A$5:$A$504,"<="&EOMONTH(SETUP!$B$8,4)) | H12: =SUMIFS(JOURNAL!$I$5:$I$504,JOURNAL!$C$5:$C$504,$A12,JOURNAL!$A$5:$A$504,">="&DATE(YEAR(SETUP!$B$8),MONTH(SETUP!$B$8)+5,1),JOURNAL!$A$5:$A$504,"<="&EOMONTH(SETUP!$B$8,5))-SUMIFS(JOURNAL!$J$5:$J$504,JOURNAL!$C$5:$C$504,$A12,JOURNAL!$A$5:$A$504,">="&DATE(YEAR(SETUP!$B$8),MONTH(SETUP!$B$8)+5,1),JOURNAL!$A$5:$A$504,"<="&EOMONTH(SETUP!$B$8,5)) | I12: =SUMIFS(JOURNAL!$I$5:$I$504,JOURNAL!$C$5:$C$504,$A12,JOURNAL!$A$5:$A$504,">="&DATE(YEAR(SETUP!$B$8),MONTH(SETUP!$B$8)+6,1),JOURNAL!$A$5:$A$504,"<="&EOMONTH(SETUP!$B$8,6))-SUMIFS(JOURNAL!$J$5:$J$504,JOURNAL!$C$5:$C$504,$A12,JOURNAL!$A$5:$A$504,">="&DATE(YEAR(SETUP!$B$8),MONTH(SETUP!$B$8)+6,1),JOURNAL!$A$5:$A$504,"<="&EOMONTH(SETUP!$B$8,6)) | J12: =SUMIFS(JOURNAL!$I$5:$I$504,JOURNAL!$C$5:$C$504,$A12,JOURNAL!$A$5:$A$504,">="&DATE(YEAR(SETUP!$B$8),MONTH(SETUP!$B$8)+7,1),JOURNAL!$A$5:$A$504,"<="&EOMONTH(SETUP!$B$8,7))-SUMIFS(JOURNAL!$J$5:$J$504,JOURNAL!$C$5:$C$504,$A12,JOURNAL!$A$5:$A$504,">="&DATE(YEAR(SETUP!$B$8),MONTH(SETUP!$B$8)+7,1),JOURNAL!$A$5:$A$504,"<="&EOMONTH(SETUP!$B$8,7)) | K12: =SUMIFS(JOURNAL!$I$5:$I$504,JOURNAL!$C$5:$C$504,$A12,JOURNAL!$A$5:$A$504,">="&DATE(YEAR(SETUP!$B$8),MONTH(SETUP!$B$8)+8,1),JOURNAL!$A$5:$A$504,"<="&EOMONTH(SETUP!$B$8,8))-SUMIFS(JOURNAL!$J$5:$J$504,JOURNAL!$C$5:$C$504,$A12,JOURNAL!$A$5:$A$504,">="&DATE(YEAR(SETUP!$B$8),MONTH(SETUP!$B$8)+8,1),JOURNAL!$A$5:$A$504,"<="&EOMONTH(SETUP!$B$8,8)) | L12: =SUMIFS(JOURNAL!$I$5:$I$504,JOURNAL!$C$5:$C$504,$A12,JOURNAL!$A$5:$A$504,">="&DATE(YEAR(SETUP!$B$8),MONTH(SETUP!$B$8)+9,1),JOURNAL!$A$5:$A$504,"<="&EOMONTH(SETUP!$B$8,9))-SUMIFS(JOURNAL!$J$5:$J$504,JOURNAL!$C$5:$C$504,$A12,JOURNAL!$A$5:$A$504,">="&DATE(YEAR(SETUP!$B$8),MONTH(SETUP!$B$8)+9,1),JOURNAL!$A$5:$A$504,"<="&EOMONTH(SETUP!$B$8,9)) | M12: =SUMIFS(JOURNAL!$I$5:$I$504,JOURNAL!$C$5:$C$504,$A12,JOURNAL!$A$5:$A$504,">="&DATE(YEAR(SETUP!$B$8),MONTH(SETUP!$B$8)+10,1),JOURNAL!$A$5:$A$504,"<="&EOMONTH(SETUP!$B$8,10))-SUMIFS(JOURNAL!$J$5:$J$504,JOURNAL!$C$5:$C$504,$A12,JOURNAL!$A$5:$A$504,">="&DATE(YEAR(SETUP!$B$8),MONTH(SETUP!$B$8)+10,1),JOURNAL!$A$5:$A$504,"<="&EOMONTH(SETUP!$B$8,10)) | N12: =SUMIFS(JOURNAL!$I$5:$I$504,JOURNAL!$C$5:$C$504,$A12,JOURNAL!$A$5:$A$504,">="&DATE(YEAR(SETUP!$B$8),MONTH(SETUP!$B$8)+11,1),JOURNAL!$A$5:$A$504,"<="&EOMONTH(SETUP!$B$8,11))-SUMIFS(JOURNAL!$J$5:$J$504,JOURNAL!$C$5:$C$504,$A12,JOURNAL!$A$5:$A$504,">="&DATE(YEAR(SETUP!$B$8),MONTH(SETUP!$B$8)+11,1),JOURNAL!$A$5:$A$504,"<="&EOMONTH(SETUP!$B$8,11)) | O12: =SUM(C12:N12)
A13: 1300 | B13: Input VAT recoverable | C13: =SUMIFS(JOURNAL!$I$5:$I$504,JOURNAL!$C$5:$C$504,$A13,JOURNAL!$A$5:$A$504,">="&DATE(YEAR(SETUP!$B$8),MONTH(SETUP!$B$8)+0,1),JOURNAL!$A$5:$A$504,"<="&EOMONTH(SETUP!$B$8,0))-SUMIFS(JOURNAL!$J$5:$J$504,JOURNAL!$C$5:$C$504,$A13,JOURNAL!$A$5:$A$504,">="&DATE(YEAR(SETUP!$B$8),MONTH(SETUP!$B$8)+0,1),JOURNAL!$A$5:$A$504,"<="&EOMONTH(SETUP!$B$8,0)) | D13: =SUMIFS(JOURNAL!$I$5:$I$504,JOURNAL!$C$5:$C$504,$A13,JOURNAL!$A$5:$A$504,">="&DATE(YEAR(SETUP!$B$8),MONTH(SETUP!$B$8)+1,1),JOURNAL!$A$5:$A$504,"<="&EOMONTH(SETUP!$B$8,1))-SUMIFS(JOURNAL!$J$5:$J$504,JOURNAL!$C$5:$C$504,$A13,JOURNAL!$A$5:$A$504,">="&DATE(YEAR(SETUP!$B$8),MONTH(SETUP!$B$8)+1,1),JOURNAL!$A$5:$A$504,"<="&EOMONTH(SETUP!$B$8,1)) | E13: =SUMIFS(JOURNAL!$I$5:$I$504,JOURNAL!$C$5:$C$504,$A13,JOURNAL!$A$5:$A$504,">="&DATE(YEAR(SETUP!$B$8),MONTH(SETUP!$B$8)+2,1),JOURNAL!$A$5:$A$504,"<="&EOMONTH(SETUP!$B$8,2))-SUMIFS(JOURNAL!$J$5:$J$504,JOURNAL!$C$5:$C$504,$A13,JOURNAL!$A$5:$A$504,">="&DATE(YEAR(SETUP!$B$8),MONTH(SETUP!$B$8)+2,1),JOURNAL!$A$5:$A$504,"<="&EOMONTH(SETUP!$B$8,2)) | F13: =SUMIFS(JOURNAL!$I$5:$I$504,JOURNAL!$C$5:$C$504,$A13,JOURNAL!$A$5:$A$504,">="&DATE(YEAR(SETUP!$B$8),MONTH(SETUP!$B$8)+3,1),JOURNAL!$A$5:$A$504,"<="&EOMONTH(SETUP!$B$8,3))-SUMIFS(JOURNAL!$J$5:$J$504,JOURNAL!$C$5:$C$504,$A13,JOURNAL!$A$5:$A$504,">="&DATE(YEAR(SETUP!$B$8),MONTH(SETUP!$B$8)+3,1),JOURNAL!$A$5:$A$504,"<="&EOMONTH(SETUP!$B$8,3)) | G13: =SUMIFS(JOURNAL!$I$5:$I$504,JOURNAL!$C$5:$C$504,$A13,JOURNAL!$A$5:$A$504,">="&DATE(YEAR(SETUP!$B$8),MONTH(SETUP!$B$8)+4,1),JOURNAL!$A$5:$A$504,"<="&EOMONTH(SETUP!$B$8,4))-SUMIFS(JOURNAL!$J$5:$J$504,JOURNAL!$C$5:$C$504,$A13,JOURNAL!$A$5:$A$504,">="&DATE(YEAR(SETUP!$B$8),MONTH(SETUP!$B$8)+4,1),JOURNAL!$A$5:$A$504,"<="&EOMONTH(SETUP!$B$8,4)) | H13: =SUMIFS(JOURNAL!$I$5:$I$504,JOURNAL!$C$5:$C$504,$A13,JOURNAL!$A$5:$A$504,">="&DATE(YEAR(SETUP!$B$8),MONTH(SETUP!$B$8)+5,1),JOURNAL!$A$5:$A$504,"<="&EOMONTH(SETUP!$B$8,5))-SUMIFS(JOURNAL!$J$5:$J$504,JOURNAL!$C$5:$C$504,$A13,JOURNAL!$A$5:$A$504,">="&DATE(YEAR(SETUP!$B$8),MONTH(SETUP!$B$8)+5,1),JOURNAL!$A$5:$A$504,"<="&EOMONTH(SETUP!$B$8,5)) | I13: =SUMIFS(JOURNAL!$I$5:$I$504,JOURNAL!$C$5:$C$504,$A13,JOURNAL!$A$5:$A$504,">="&DATE(YEAR(SETUP!$B$8),MONTH(SETUP!$B$8)+6,1),JOURNAL!$A$5:$A$504,"<="&EOMONTH(SETUP!$B$8,6))-SUMIFS(JOURNAL!$J$5:$J$504,JOURNAL!$C$5:$C$504,$A13,JOURNAL!$A$5:$A$504,">="&DATE(YEAR(SETUP!$B$8),MONTH(SETUP!$B$8)+6,1),JOURNAL!$A$5:$A$504,"<="&EOMONTH(SETUP!$B$8,6)) | J13: =SUMIFS(JOURNAL!$I$5:$I$504,JOURNAL!$C$5:$C$504,$A13,JOURNAL!$A$5:$A$504,">="&DATE(YEAR(SETUP!$B$8),MONTH(SETUP!$B$8)+7,1),JOURNAL!$A$5:$A$504,"<="&EOMONTH(SETUP!$B$8,7))-SUMIFS(JOURNAL!$J$5:$J$504,JOURNAL!$C$5:$C$504,$A13,JOURNAL!$A$5:$A$504,">="&DATE(YEAR(SETUP!$B$8),MONTH(SETUP!$B$8)+7,1),JOURNAL!$A$5:$A$504,"<="&EOMONTH(SETUP!$B$8,7)) | K13: =SUMIFS(JOURNAL!$I$5:$I$504,JOURNAL!$C$5:$C$504,$A13,JOURNAL!$A$5:$A$504,">="&DATE(YEAR(SETUP!$B$8),MONTH(SETUP!$B$8)+8,1),JOURNAL!$A$5:$A$504,"<="&EOMONTH(SETUP!$B$8,8))-SUMIFS(JOURNAL!$J$5:$J$504,JOURNAL!$C$5:$C$504,$A13,JOURNAL!$A$5:$A$504,">="&DATE(YEAR(SETUP!$B$8),MONTH(SETUP!$B$8)+8,1),JOURNAL!$A$5:$A$504,"<="&EOMONTH(SETUP!$B$8,8)) | L13: =SUMIFS(JOURNAL!$I$5:$I$504,JOURNAL!$C$5:$C$504,$A13,JOURNAL!$A$5:$A$504,">="&DATE(YEAR(SETUP!$B$8),MONTH(SETUP!$B$8)+9,1),JOURNAL!$A$5:$A$504,"<="&EOMONTH(SETUP!$B$8,9))-SUMIFS(JOURNAL!$J$5:$J$504,JOURNAL!$C$5:$C$504,$A13,JOURNAL!$A$5:$A$504,">="&DATE(YEAR(SETUP!$B$8),MONTH(SETUP!$B$8)+9,1),JOURNAL!$A$5:$A$504,"<="&EOMONTH(SETUP!$B$8,9)) | M13: =SUMIFS(JOURNAL!$I$5:$I$504,JOURNAL!$C$5:$C$504,$A13,JOURNAL!$A$5:$A$504,">="&DATE(YEAR(SETUP!$B$8),MONTH(SETUP!$B$8)+10,1),JOURNAL!$A$5:$A$504,"<="&EOMONTH(SETUP!$B$8,10))-SUMIFS(JOURNAL!$J$5:$J$504,JOURNAL!$C$5:$C$504,$A13,JOURNAL!$A$5:$A$504,">="&DATE(YEAR(SETUP!$B$8),MONTH(SETUP!$B$8)+10,1),JOURNAL!$A$5:$A$504,"<="&EOMONTH(SETUP!$B$8,10)) | N13: =SUMIFS(JOURNAL!$I$5:$I$504,JOURNAL!$C$5:$C$504,$A13,JOURNAL!$A$5:$A$504,">="&DATE(YEAR(SETUP!$B$8),MONTH(SETUP!$B$8)+11,1),JOURNAL!$A$5:$A$504,"<="&EOMONTH(SETUP!$B$8,11))-SUMIFS(JOURNAL!$J$5:$J$504,JOURNAL!$C$5:$C$504,$A13,JOURNAL!$A$5:$A$504,">="&DATE(YEAR(SETUP!$B$8),MONTH(SETUP!$B$8)+11,1),JOURNAL!$A$5:$A$504,"<="&EOMONTH(SETUP!$B$8,11)) | O13: =SUM(C13:N13)
A14: 1500 | B14: Plant and equipment at cost | C14: =SUMIFS(JOURNAL!$I$5:$I$504,JOURNAL!$C$5:$C$504,$A14,JOURNAL!$A$5:$A$504,">="&DATE(YEAR(SETUP!$B$8),MONTH(SETUP!$B$8)+0,1),JOURNAL!$A$5:$A$504,"<="&EOMONTH(SETUP!$B$8,0))-SUMIFS(JOURNAL!$J$5:$J$504,JOURNAL!$C$5:$C$504,$A14,JOURNAL!$A$5:$A$504,">="&DATE(YEAR(SETUP!$B$8),MONTH(SETUP!$B$8)+0,1),JOURNAL!$A$5:$A$504,"<="&EOMONTH(SETUP!$B$8,0)) | D14: =SUMIFS(JOURNAL!$I$5:$I$504,JOURNAL!$C$5:$C$504,$A14,JOURNAL!$A$5:$A$504,">="&DATE(YEAR(SETUP!$B$8),MONTH(SETUP!$B$8)+1,1),JOURNAL!$A$5:$A$504,"<="&EOMONTH(SETUP!$B$8,1))-SUMIFS(JOURNAL!$J$5:$J$504,JOURNAL!$C$5:$C$504,$A14,JOURNAL!$A$5:$A$504,">="&DATE(YEAR(SETUP!$B$8),MONTH(SETUP!$B$8)+1,1),JOURNAL!$A$5:$A$504,"<="&EOMONTH(SETUP!$B$8,1)) | E14: =SUMIFS(JOURNAL!$I$5:$I$504,JOURNAL!$C$5:$C$504,$A14,JOURNAL!$A$5:$A$504,">="&DATE(YEAR(SETUP!$B$8),MONTH(SETUP!$B$8)+2,1),JOURNAL!$A$5:$A$504,"<="&EOMONTH(SETUP!$B$8,2))-SUMIFS(JOURNAL!$J$5:$J$504,JOURNAL!$C$5:$C$504,$A14,JOURNAL!$A$5:$A$504,">="&DATE(YEAR(SETUP!$B$8),MONTH(SETUP!$B$8)+2,1),JOURNAL!$A$5:$A$504,"<="&EOMONTH(SETUP!$B$8,2)) | F14: =SUMIFS(JOURNAL!$I$5:$I$504,JOURNAL!$C$5:$C$504,$A14,JOURNAL!$A$5:$A$504,">="&DATE(YEAR(SETUP!$B$8),MONTH(SETUP!$B$8)+3,1),JOURNAL!$A$5:$A$504,"<="&EOMONTH(SETUP!$B$8,3))-SUMIFS(JOURNAL!$J$5:$J$504,JOURNAL!$C$5:$C$504,$A14,JOURNAL!$A$5:$A$504,">="&DATE(YEAR(SETUP!$B$8),MONTH(SETUP!$B$8)+3,1),JOURNAL!$A$5:$A$504,"<="&EOMONTH(SETUP!$B$8,3)) | G14: =SUMIFS(JOURNAL!$I$5:$I$504,JOURNAL!$C$5:$C$504,$A14,JOURNAL!$A$5:$A$504,">="&DATE(YEAR(SETUP!$B$8),MONTH(SETUP!$B$8)+4,1),JOURNAL!$A$5:$A$504,"<="&EOMONTH(SETUP!$B$8,4))-SUMIFS(JOURNAL!$J$5:$J$504,JOURNAL!$C$5:$C$504,$A14,JOURNAL!$A$5:$A$504,">="&DATE(YEAR(SETUP!$B$8),MONTH(SETUP!$B$8)+4,1),JOURNAL!$A$5:$A$504,"<="&EOMONTH(SETUP!$B$8,4)) | H14: =SUMIFS(JOURNAL!$I$5:$I$504,JOURNAL!$C$5:$C$504,$A14,JOURNAL!$A$5:$A$504,">="&DATE(YEAR(SETUP!$B$8),MONTH(SETUP!$B$8)+5,1),JOURNAL!$A$5:$A$504,"<="&EOMONTH(SETUP!$B$8,5))-SUMIFS(JOURNAL!$J$5:$J$504,JOURNAL!$C$5:$C$504,$A14,JOURNAL!$A$5:$A$504,">="&DATE(YEAR(SETUP!$B$8),MONTH(SETUP!$B$8)+5,1),JOURNAL!$A$5:$A$504,"<="&EOMONTH(SETUP!$B$8,5)) | I14: =SUMIFS(JOURNAL!$I$5:$I$504,JOURNAL!$C$5:$C$504,$A14,JOURNAL!$A$5:$A$504,">="&DATE(YEAR(SETUP!$B$8),MONTH(SETUP!$B$8)+6,1),JOURNAL!$A$5:$A$504,"<="&EOMONTH(SETUP!$B$8,6))-SUMIFS(JOURNAL!$J$5:$J$504,JOURNAL!$C$5:$C$504,$A14,JOURNAL!$A$5:$A$504,">="&DATE(YEAR(SETUP!$B$8),MONTH(SETUP!$B$8)+6,1),JOURNAL!$A$5:$A$504,"<="&EOMONTH(SETUP!$B$8,6)) | J14: =SUMIFS(JOURNAL!$I$5:$I$504,JOURNAL!$C$5:$C$504,$A14,JOURNAL!$A$5:$A$504,">="&DATE(YEAR(SETUP!$B$8),MONTH(SETUP!$B$8)+7,1),JOURNAL!$A$5:$A$504,"<="&EOMONTH(SETUP!$B$8,7))-SUMIFS(JOURNAL!$J$5:$J$504,JOURNAL!$C$5:$C$504,$A14,JOURNAL!$A$5:$A$504,">="&DATE(YEAR(SETUP!$B$8),MONTH(SETUP!$B$8)+7,1),JOURNAL!$A$5:$A$504,"<="&EOMONTH(SETUP!$B$8,7)) | K14: =SUMIFS(JOURNAL!$I$5:$I$504,JOURNAL!$C$5:$C$504,$A14,JOURNAL!$A$5:$A$504,">="&DATE(YEAR(SETUP!$B$8),MONTH(SETUP!$B$8)+8,1),JOURNAL!$A$5:$A$504,"<="&EOMONTH(SETUP!$B$8,8))-SUMIFS(JOURNAL!$J$5:$J$504,JOURNAL!$C$5:$C$504,$A14,JOURNAL!$A$5:$A$504,">="&DATE(YEAR(SETUP!$B$8),MONTH(SETUP!$B$8)+8,1),JOURNAL!$A$5:$A$504,"<="&EOMONTH(SETUP!$B$8,8)) | L14: =SUMIFS(JOURNAL!$I$5:$I$504,JOURNAL!$C$5:$C$504,$A14,JOURNAL!$A$5:$A$504,">="&DATE(YEAR(SETUP!$B$8),MONTH(SETUP!$B$8)+9,1),JOURNAL!$A$5:$A$504,"<="&EOMONTH(SETUP!$B$8,9))-SUMIFS(JOURNAL!$J$5:$J$504,JOURNAL!$C$5:$C$504,$A14,JOURNAL!$A$5:$A$504,">="&DATE(YEAR(SETUP!$B$8),MONTH(SETUP!$B$8)+9,1),JOURNAL!$A$5:$A$504,"<="&EOMONTH(SETUP!$B$8,9)) | M14: =SUMIFS(JOURNAL!$I$5:$I$504,JOURNAL!$C$5:$C$504,$A14,JOURNAL!$A$5:$A$504,">="&DATE(YEAR(SETUP!$B$8),MONTH(SETUP!$B$8)+10,1),JOURNAL!$A$5:$A$504,"<="&EOMONTH(SETUP!$B$8,10))-SUMIFS(JOURNAL!$J$5:$J$504,JOURNAL!$C$5:$C$504,$A14,JOURNAL!$A$5:$A$504,">="&DATE(YEAR(SETUP!$B$8),MONTH(SETUP!$B$8)+10,1),JOURNAL!$A$5:$A$504,"<="&EOMONTH(SETUP!$B$8,10)) | N14: =SUMIFS(JOURNAL!$I$5:$I$504,JOURNAL!$C$5:$C$504,$A14,JOURNAL!$A$5:$A$504,">="&DATE(YEAR(SETUP!$B$8),MONTH(SETUP!$B$8)+11,1),JOURNAL!$A$5:$A$504,"<="&EOMONTH(SETUP!$B$8,11))-SUMIFS(JOURNAL!$J$5:$J$504,JOURNAL!$C$5:$C$504,$A14,JOURNAL!$A$5:$A$504,">="&DATE(YEAR(SETUP!$B$8),MONTH(SETUP!$B$8)+11,1),JOURNAL!$A$5:$A$504,"<="&EOMONTH(SETUP!$B$8,11)) | O14: =SUM(C14:N14)
A15: 1510 | B15: Accumulated depreciation | C15: =SUMIFS(JOURNAL!$I$5:$I$504,JOURNAL!$C$5:$C$504,$A15,JOURNAL!$A$5:$A$504,">="&DATE(YEAR(SETUP!$B$8),MONTH(SETUP!$B$8)+0,1),JOURNAL!$A$5:$A$504,"<="&EOMONTH(SETUP!$B$8,0))-SUMIFS(JOURNAL!$J$5:$J$504,JOURNAL!$C$5:$C$504,$A15,JOURNAL!$A$5:$A$504,">="&DATE(YEAR(SETUP!$B$8),MONTH(SETUP!$B$8)+0,1),JOURNAL!$A$5:$A$504,"<="&EOMONTH(SETUP!$B$8,0)) | D15: =SUMIFS(JOURNAL!$I$5:$I$504,JOURNAL!$C$5:$C$504,$A15,JOURNAL!$A$5:$A$504,">="&DATE(YEAR(SETUP!$B$8),MONTH(SETUP!$B$8)+1,1),JOURNAL!$A$5:$A$504,"<="&EOMONTH(SETUP!$B$8,1))-SUMIFS(JOURNAL!$J$5:$J$504,JOURNAL!$C$5:$C$504,$A15,JOURNAL!$A$5:$A$504,">="&DATE(YEAR(SETUP!$B$8),MONTH(SETUP!$B$8)+1,1),JOURNAL!$A$5:$A$504,"<="&EOMONTH(SETUP!$B$8,1)) | E15: =SUMIFS(JOURNAL!$I$5:$I$504,JOURNAL!$C$5:$C$504,$A15,JOURNAL!$A$5:$A$504,">="&DATE(YEAR(SETUP!$B$8),MONTH(SETUP!$B$8)+2,1),JOURNAL!$A$5:$A$504,"<="&EOMONTH(SETUP!$B$8,2))-SUMIFS(JOURNAL!$J$5:$J$504,JOURNAL!$C$5:$C$504,$A15,JOURNAL!$A$5:$A$504,">="&DATE(YEAR(SETUP!$B$8),MONTH(SETUP!$B$8)+2,1),JOURNAL!$A$5:$A$504,"<="&EOMONTH(SETUP!$B$8,2)) | F15: =SUMIFS(JOURNAL!$I$5:$I$504,JOURNAL!$C$5:$C$504,$A15,JOURNAL!$A$5:$A$504,">="&DATE(YEAR(SETUP!$B$8),MONTH(SETUP!$B$8)+3,1),JOURNAL!$A$5:$A$504,"<="&EOMONTH(SETUP!$B$8,3))-SUMIFS(JOURNAL!$J$5:$J$504,JOURNAL!$C$5:$C$504,$A15,JOURNAL!$A$5:$A$504,">="&DATE(YEAR(SETUP!$B$8),MONTH(SETUP!$B$8)+3,1),JOURNAL!$A$5:$A$504,"<="&EOMONTH(SETUP!$B$8,3)) | G15: =SUMIFS(JOURNAL!$I$5:$I$504,JOURNAL!$C$5:$C$504,$A15,JOURNAL!$A$5:$A$504,">="&DATE(YEAR(SETUP!$B$8),MONTH(SETUP!$B$8)+4,1),JOURNAL!$A$5:$A$504,"<="&EOMONTH(SETUP!$B$8,4))-SUMIFS(JOURNAL!$J$5:$J$504,JOURNAL!$C$5:$C$504,$A15,JOURNAL!$A$5:$A$504,">="&DATE(YEAR(SETUP!$B$8),MONTH(SETUP!$B$8)+4,1),JOURNAL!$A$5:$A$504,"<="&EOMONTH(SETUP!$B$8,4)) | H15: =SUMIFS(JOURNAL!$I$5:$I$504,JOURNAL!$C$5:$C$504,$A15,JOURNAL!$A$5:$A$504,">="&DATE(YEAR(SETUP!$B$8),MONTH(SETUP!$B$8)+5,1),JOURNAL!$A$5:$A$504,"<="&EOMONTH(SETUP!$B$8,5))-SUMIFS(JOURNAL!$J$5:$J$504,JOURNAL!$C$5:$C$504,$A15,JOURNAL!$A$5:$A$504,">="&DATE(YEAR(SETUP!$B$8),MONTH(SETUP!$B$8)+5,1),JOURNAL!$A$5:$A$504,"<="&EOMONTH(SETUP!$B$8,5)) | I15: =SUMIFS(JOURNAL!$I$5:$I$504,JOURNAL!$C$5:$C$504,$A15,JOURNAL!$A$5:$A$504,">="&DATE(YEAR(SETUP!$B$8),MONTH(SETUP!$B$8)+6,1),JOURNAL!$A$5:$A$504,"<="&EOMONTH(SETUP!$B$8,6))-SUMIFS(JOURNAL!$J$5:$J$504,JOURNAL!$C$5:$C$504,$A15,JOURNAL!$A$5:$A$504,">="&DATE(YEAR(SETUP!$B$8),MONTH(SETUP!$B$8)+6,1),JOURNAL!$A$5:$A$504,"<="&EOMONTH(SETUP!$B$8,6)) | J15: =SUMIFS(JOURNAL!$I$5:$I$504,JOURNAL!$C$5:$C$504,$A15,JOURNAL!$A$5:$A$504,">="&DATE(YEAR(SETUP!$B$8),MONTH(SETUP!$B$8)+7,1),JOURNAL!$A$5:$A$504,"<="&EOMONTH(SETUP!$B$8,7))-SUMIFS(JOURNAL!$J$5:$J$504,JOURNAL!$C$5:$C$504,$A15,JOURNAL!$A$5:$A$504,">="&DATE(YEAR(SETUP!$B$8),MONTH(SETUP!$B$8)+7,1),JOURNAL!$A$5:$A$504,"<="&EOMONTH(SETUP!$B$8,7)) | K15: =SUMIFS(JOURNAL!$I$5:$I$504,JOURNAL!$C$5:$C$504,$A15,JOURNAL!$A$5:$A$504,">="&DATE(YEAR(SETUP!$B$8),MONTH(SETUP!$B$8)+8,1),JOURNAL!$A$5:$A$504,"<="&EOMONTH(SETUP!$B$8,8))-SUMIFS(JOURNAL!$J$5:$J$504,JOURNAL!$C$5:$C$504,$A15,JOURNAL!$A$5:$A$504,">="&DATE(YEAR(SETUP!$B$8),MONTH(SETUP!$B$8)+8,1),JOURNAL!$A$5:$A$504,"<="&EOMONTH(SETUP!$B$8,8)) | L15: =SUMIFS(JOURNAL!$I$5:$I$504,JOURNAL!$C$5:$C$504,$A15,JOURNAL!$A$5:$A$504,">="&DATE(YEAR(SETUP!$B$8),MONTH(SETUP!$B$8)+9,1),JOURNAL!$A$5:$A$504,"<="&EOMONTH(SETUP!$B$8,9))-SUMIFS(JOURNAL!$J$5:$J$504,JOURNAL!$C$5:$C$504,$A15,JOURNAL!$A$5:$A$504,">="&DATE(YEAR(SETUP!$B$8),MONTH(SETUP!$B$8)+9,1),JOURNAL!$A$5:$A$504,"<="&EOMONTH(SETUP!$B$8,9)) | M15: =SUMIFS(JOURNAL!$I$5:$I$504,JOURNAL!$C$5:$C$504,$A15,JOURNAL!$A$5:$A$504,">="&DATE(YEAR(SETUP!$B$8),MONTH(SETUP!$B$8)+10,1),JOURNAL!$A$5:$A$504,"<="&EOMONTH(SETUP!$B$8,10))-SUMIFS(JOURNAL!$J$5:$J$504,JOURNAL!$C$5:$C$504,$A15,JOURNAL!$A$5:$A$504,">="&DATE(YEAR(SETUP!$B$8),MONTH(SETUP!$B$8)+10,1),JOURNAL!$A$5:$A$504,"<="&EOMONTH(SETUP!$B$8,10)) | N15: =SUMIFS(JOURNAL!$I$5:$I$504,JOURNAL!$C$5:$C$504,$A15,JOURNAL!$A$5:$A$504,">="&DATE(YEAR(SETUP!$B$8),MONTH(SETUP!$B$8)+11,1),JOURNAL!$A$5:$A$504,"<="&EOMONTH(SETUP!$B$8,11))-SUMIFS(JOURNAL!$J$5:$J$504,JOURNAL!$C$5:$C$504,$A15,JOURNAL!$A$5:$A$504,">="&DATE(YEAR(SETUP!$B$8),MONTH(SETUP!$B$8)+11,1),JOURNAL!$A$5:$A$504,"<="&EOMONTH(SETUP!$B$8,11)) | O15: =SUM(C15:N15)
A16: 2000 | B16: Trade payables | C16: =SUMIFS(JOURNAL!$I$5:$I$504,JOURNAL!$C$5:$C$504,$A16,JOURNAL!$A$5:$A$504,">="&DATE(YEAR(SETUP!$B$8),MONTH(SETUP!$B$8)+0,1),JOURNAL!$A$5:$A$504,"<="&EOMONTH(SETUP!$B$8,0))-SUMIFS(JOURNAL!$J$5:$J$504,JOURNAL!$C$5:$C$504,$A16,JOURNAL!$A$5:$A$504,">="&DATE(YEAR(SETUP!$B$8),MONTH(SETUP!$B$8)+0,1),JOURNAL!$A$5:$A$504,"<="&EOMONTH(SETUP!$B$8,0)) | D16: =SUMIFS(JOURNAL!$I$5:$I$504,JOURNAL!$C$5:$C$504,$A16,JOURNAL!$A$5:$A$504,">="&DATE(YEAR(SETUP!$B$8),MONTH(SETUP!$B$8)+1,1),JOURNAL!$A$5:$A$504,"<="&EOMONTH(SETUP!$B$8,1))-SUMIFS(JOURNAL!$J$5:$J$504,JOURNAL!$C$5:$C$504,$A16,JOURNAL!$A$5:$A$504,">="&DATE(YEAR(SETUP!$B$8),MONTH(SETUP!$B$8)+1,1),JOURNAL!$A$5:$A$504,"<="&EOMONTH(SETUP!$B$8,1)) | E16: =SUMIFS(JOURNAL!$I$5:$I$504,JOURNAL!$C$5:$C$504,$A16,JOURNAL!$A$5:$A$504,">="&DATE(YEAR(SETUP!$B$8),MONTH(SETUP!$B$8)+2,1),JOURNAL!$A$5:$A$504,"<="&EOMONTH(SETUP!$B$8,2))-SUMIFS(JOURNAL!$J$5:$J$504,JOURNAL!$C$5:$C$504,$A16,JOURNAL!$A$5:$A$504,">="&DATE(YEAR(SETUP!$B$8),MONTH(SETUP!$B$8)+2,1),JOURNAL!$A$5:$A$504,"<="&EOMONTH(SETUP!$B$8,2)) | F16: =SUMIFS(JOURNAL!$I$5:$I$504,JOURNAL!$C$5:$C$504,$A16,JOURNAL!$A$5:$A$504,">="&DATE(YEAR(SETUP!$B$8),MONTH(SETUP!$B$8)+3,1),JOURNAL!$A$5:$A$504,"<="&EOMONTH(SETUP!$B$8,3))-SUMIFS(JOURNAL!$J$5:$J$504,JOURNAL!$C$5:$C$504,$A16,JOURNAL!$A$5:$A$504,">="&DATE(YEAR(SETUP!$B$8),MONTH(SETUP!$B$8)+3,1),JOURNAL!$A$5:$A$504,"<="&EOMONTH(SETUP!$B$8,3)) | G16: =SUMIFS(JOURNAL!$I$5:$I$504,JOURNAL!$C$5:$C$504,$A16,JOURNAL!$A$5:$A$504,">="&DATE(YEAR(SETUP!$B$8),MONTH(SETUP!$B$8)+4,1),JOURNAL!$A$5:$A$504,"<="&EOMONTH(SETUP!$B$8,4))-SUMIFS(JOURNAL!$J$5:$J$504,JOURNAL!$C$5:$C$504,$A16,JOURNAL!$A$5:$A$504,">="&DATE(YEAR(SETUP!$B$8),MONTH(SETUP!$B$8)+4,1),JOURNAL!$A$5:$A$504,"<="&EOMONTH(SETUP!$B$8,4)) | H16: =SUMIFS(JOURNAL!$I$5:$I$504,JOURNAL!$C$5:$C$504,$A16,JOURNAL!$A$5:$A$504,">="&DATE(YEAR(SETUP!$B$8),MONTH(SETUP!$B$8)+5,1),JOURNAL!$A$5:$A$504,"<="&EOMONTH(SETUP!$B$8,5))-SUMIFS(JOURNAL!$J$5:$J$504,JOURNAL!$C$5:$C$504,$A16,JOURNAL!$A$5:$A$504,">="&DATE(YEAR(SETUP!$B$8),MONTH(SETUP!$B$8)+5,1),JOURNAL!$A$5:$A$504,"<="&EOMONTH(SETUP!$B$8,5)) | I16: =SUMIFS(JOURNAL!$I$5:$I$504,JOURNAL!$C$5:$C$504,$A16,JOURNAL!$A$5:$A$504,">="&DATE(YEAR(SETUP!$B$8),MONTH(SETUP!$B$8)+6,1),JOURNAL!$A$5:$A$504,"<="&EOMONTH(SETUP!$B$8,6))-SUMIFS(JOURNAL!$J$5:$J$504,JOURNAL!$C$5:$C$504,$A16,JOURNAL!$A$5:$A$504,">="&DATE(YEAR(SETUP!$B$8),MONTH(SETUP!$B$8)+6,1),JOURNAL!$A$5:$A$504,"<="&EOMONTH(SETUP!$B$8,6)) | J16: =SUMIFS(JOURNAL!$I$5:$I$504,JOURNAL!$C$5:$C$504,$A16,JOURNAL!$A$5:$A$504,">="&DATE(YEAR(SETUP!$B$8),MONTH(SETUP!$B$8)+7,1),JOURNAL!$A$5:$A$504,"<="&EOMONTH(SETUP!$B$8,7))-SUMIFS(JOURNAL!$J$5:$J$504,JOURNAL!$C$5:$C$504,$A16,JOURNAL!$A$5:$A$504,">="&DATE(YEAR(SETUP!$B$8),MONTH(SETUP!$B$8)+7,1),JOURNAL!$A$5:$A$504,"<="&EOMONTH(SETUP!$B$8,7)) | K16: =SUMIFS(JOURNAL!$I$5:$I$504,JOURNAL!$C$5:$C$504,$A16,JOURNAL!$A$5:$A$504,">="&DATE(YEAR(SETUP!$B$8),MONTH(SETUP!$B$8)+8,1),JOURNAL!$A$5:$A$504,"<="&EOMONTH(SETUP!$B$8,8))-SUMIFS(JOURNAL!$J$5:$J$504,JOURNAL!$C$5:$C$504,$A16,JOURNAL!$A$5:$A$504,">="&DATE(YEAR(SETUP!$B$8),MONTH(SETUP!$B$8)+8,1),JOURNAL!$A$5:$A$504,"<="&EOMONTH(SETUP!$B$8,8)) | L16: =SUMIFS(JOURNAL!$I$5:$I$504,JOURNAL!$C$5:$C$504,$A16,JOURNAL!$A$5:$A$504,">="&DATE(YEAR(SETUP!$B$8),MONTH(SETUP!$B$8)+9,1),JOURNAL!$A$5:$A$504,"<="&EOMONTH(SETUP!$B$8,9))-SUMIFS(JOURNAL!$J$5:$J$504,JOURNAL!$C$5:$C$504,$A16,JOURNAL!$A$5:$A$504,">="&DATE(YEAR(SETUP!$B$8),MONTH(SETUP!$B$8)+9,1),JOURNAL!$A$5:$A$504,"<="&EOMONTH(SETUP!$B$8,9)) | M16: =SUMIFS(JOURNAL!$I$5:$I$504,JOURNAL!$C$5:$C$504,$A16,JOURNAL!$A$5:$A$504,">="&DATE(YEAR(SETUP!$B$8),MONTH(SETUP!$B$8)+10,1),JOURNAL!$A$5:$A$504,"<="&EOMONTH(SETUP!$B$8,10))-SUMIFS(JOURNAL!$J$5:$J$504,JOURNAL!$C$5:$C$504,$A16,JOURNAL!$A$5:$A$504,">="&DATE(YEAR(SETUP!$B$8),MONTH(SETUP!$B$8)+10,1),JOURNAL!$A$5:$A$504,"<="&EOMONTH(SETUP!$B$8,10)) | N16: =SUMIFS(JOURNAL!$I$5:$I$504,JOURNAL!$C$5:$C$504,$A16,JOURNAL!$A$5:$A$504,">="&DATE(YEAR(SETUP!$B$8),MONTH(SETUP!$B$8)+11,1),JOURNAL!$A$5:$A$504,"<="&EOMONTH(SETUP!$B$8,11))-SUMIFS(JOURNAL!$J$5:$J$504,JOURNAL!$C$5:$C$504,$A16,JOURNAL!$A$5:$A$504,">="&DATE(YEAR(SETUP!$B$8),MONTH(SETUP!$B$8)+11,1),JOURNAL!$A$5:$A$504,"<="&EOMONTH(SETUP!$B$8,11)) | O16: =SUM(C16:N16)
... A56: 9000 | B56: Bad debt provision | C56: =SUMIFS(JOURNAL!$I$5:$I$504,JOURNAL!$C$5:$C$504,$A56,JOURNAL!$A$5:$A$504,">="&DATE(YEAR(SETUP!$B$8),MONTH(SETUP!$B$8)+0,1),JOURNAL!$A$5:$A$504,"<="&EOMONTH(SETUP!$B$8,0))-SUMIFS(JOURNAL!$J$5:$J$504,JOURNAL!$C$5:$C$504,$A56,JOURNAL!$A$5:$A$504,">="&DATE(YEAR(SETUP!$B$8),MONTH(SETUP!$B$8)+0,1),JOURNAL!$A$5:$A$504,"<="&EOMONTH(SETUP!$B$8,0)) | D56: =SUMIFS(JOURNAL!$I$5:$I$504,JOURNAL!$C$5:$C$504,$A56,JOURNAL!$A$5:$A$504,">="&DATE(YEAR(SETUP!$B$8),MONTH(SETUP!$B$8)+1,1),JOURNAL!$A$5:$A$504,"<="&EOMONTH(SETUP!$B$8,1))-SUMIFS(JOURNAL!$J$5:$J$504,JOURNAL!$C$5:$C$504,$A56,JOURNAL!$A$5:$A$504,">="&DATE(YEAR(SETUP!$B$8),MONTH(SETUP!$B$8)+1,1),JOURNAL!$A$5:$A$504,"<="&EOMONTH(SETUP!$B$8,1)) | E56: =SUMIFS(JOURNAL!$I$5:$I$504,JOURNAL!$C$5:$C$504,$A56,JOURNAL!$A$5:$A$504,">="&DATE(YEAR(SETUP!$B$8),MONTH(SETUP!$B$8)+2,1),JOURNAL!$A$5:$A$504,"<="&EOMONTH(SETUP!$B$8,2))-SUMIFS(JOURNAL!$J$5:$J$504,JOURNAL!$C$5:$C$504,$A56,JOURNAL!$A$5:$A$504,">="&DATE(YEAR(SETUP!$B$8),MONTH(SETUP!$B$8)+2,1),JOURNAL!$A$5:$A$504,"<="&EOMONTH(SETUP!$B$8,2)) | F56: =SUMIFS(JOURNAL!$I$5:$I$504,JOURNAL!$C$5:$C$504,$A56,JOURNAL!$A$5:$A$504,">="&DATE(YEAR(SETUP!$B$8),MONTH(SETUP!$B$8)+3,1),JOURNAL!$A$5:$A$504,"<="&EOMONTH(SETUP!$B$8,3))-SUMIFS(JOURNAL!$J$5:$J$504,JOURNAL!$C$5:$C$504,$A56,JOURNAL!$A$5:$A$504,">="&DATE(YEAR(SETUP!$B$8),MONTH(SETUP!$B$8)+3,1),JOURNAL!$A$5:$A$504,"<="&EOMONTH(SETUP!$B$8,3)) | G56: =SUMIFS(JOURNAL!$I$5:$I$504,JOURNAL!$C$5:$C$504,$A56,JOURNAL!$A$5:$A$504,">="&DATE(YEAR(SETUP!$B$8),MONTH(SETUP!$B$8)+4,1),JOURNAL!$A$5:$A$504,"<="&EOMONTH(SETUP!$B$8,4))-SUMIFS(JOURNAL!$J$5:$J$504,JOURNAL!$C$5:$C$504,$A56,JOURNAL!$A$5:$A$504,">="&DATE(YEAR(SETUP!$B$8),MONTH(SETUP!$B$8)+4,1),JOURNAL!$A$5:$A$504,"<="&EOMONTH(SETUP!$B$8,4)) | H56: =SUMIFS(JOURNAL!$I$5:$I$504,JOURNAL!$C$5:$C$504,$A56,JOURNAL!$A$5:$A$504,">="&DATE(YEAR(SETUP!$B$8),MONTH(SETUP!$B$8)+5,1),JOURNAL!$A$5:$A$504,"<="&EOMONTH(SETUP!$B$8,5))-SUMIFS(JOURNAL!$J$5:$J$504,JOURNAL!$C$5:$C$504,$A56,JOURNAL!$A$5:$A$504,">="&DATE(YEAR(SETUP!$B$8),MONTH(SETUP!$B$8)+5,1),JOURNAL!$A$5:$A$504,"<="&EOMONTH(SETUP!$B$8,5)) | I56: =SUMIFS(JOURNAL!$I$5:$I$504,JOURNAL!$C$5:$C$504,$A56,JOURNAL!$A$5:$A$504,">="&DATE(YEAR(SETUP!$B$8),MONTH(SETUP!$B$8)+6,1),JOURNAL!$A$5:$A$504,"<="&EOMONTH(SETUP!$B$8,6))-SUMIFS(JOURNAL!$J$5:$J$504,JOURNAL!$C$5:$C$504,$A56,JOURNAL!$A$5:$A$504,">="&DATE(YEAR(SETUP!$B$8),MONTH(SETUP!$B$8)+6,1),JOURNAL!$A$5:$A$504,"<="&EOMONTH(SETUP!$B$8,6)) | J56: =SUMIFS(JOURNAL!$I$5:$I$504,JOURNAL!$C$5:$C$504,$A56,JOURNAL!$A$5:$A$504,">="&DATE(YEAR(SETUP!$B$8),MONTH(SETUP!$B$8)+7,1),JOURNAL!$A$5:$A$504,"<="&EOMONTH(SETUP!$B$8,7))-SUMIFS(JOURNAL!$J$5:$J$504,JOURNAL!$C$5:$C$504,$A56,JOURNAL!$A$5:$A$504,">="&DATE(YEAR(SETUP!$B$8),MONTH(SETUP!$B$8)+7,1),JOURNAL!$A$5:$A$504,"<="&EOMONTH(SETUP!$B$8,7)) | K56: =SUMIFS(JOURNAL!$I$5:$I$504,JOURNAL!$C$5:$C$504,$A56,JOURNAL!$A$5:$A$504,">="&DATE(YEAR(SETUP!$B$8),MONTH(SETUP!$B$8)+8,1),JOURNAL!$A$5:$A$504,"<="&EOMONTH(SETUP!$B$8,8))-SUMIFS(JOURNAL!$J$5:$J$504,JOURNAL!$C$5:$C$504,$A56,JOURNAL!$A$5:$A$504,">="&DATE(YEAR(SETUP!$B$8),MONTH(SETUP!$B$8)+8,1),JOURNAL!$A$5:$A$504,"<="&EOMONTH(SETUP!$B$8,8)) | L56: =SUMIFS(JOURNAL!$I$5:$I$504,JOURNAL!$C$5:$C$504,$A56,JOURNAL!$A$5:$A$504,">="&DATE(YEAR(SETUP!$B$8),MONTH(SETUP!$B$8)+9,1),JOURNAL!$A$5:$A$504,"<="&EOMONTH(SETUP!$B$8,9))-SUMIFS(JOURNAL!$J$5:$J$504,JOURNAL!$C$5:$C$504,$A56,JOURNAL!$A$5:$A$504,">="&DATE(YEAR(SETUP!$B$8),MONTH(SETUP!$B$8)+9,1),JOURNAL!$A$5:$A$504,"<="&EOMONTH(SETUP!$B$8,9)) | M56: =SUMIFS(JOURNAL!$I$5:$I$504,JOURNAL!$C$5:$C$504,$A56,JOURNAL!$A$5:$A$504,">="&DATE(YEAR(SETUP!$B$8),MONTH(SETUP!$B$8)+10,1),JOURNAL!$A$5:$A$504,"<="&EOMONTH(SETUP!$B$8,10))-SUMIFS(JOURNAL!$J$5:$J$504,JOURNAL!$C$5:$C$504,$A56,JOURNAL!$A$5:$A$504,">="&DATE(YEAR(SETUP!$B$8),MONTH(SETUP!$B$8)+10,1),JOURNAL!$A$5:$A$504,"<="&EOMONTH(SETUP!$B$8,10)) | N56: =SUMIFS(JOURNAL!$I$5:$I$504,JOURNAL!$C$5:$C$504,$A56,JOURNAL!$A$5:$A$504,">="&DATE(YEAR(SETUP!$B$8),MONTH(SETUP!$B$8)+11,1),JOURNAL!$A$5:$A$504,"<="&EOMONTH(SETUP!$B$8,11))-SUMIFS(JOURNAL!$J$5:$J$504,JOURNAL!$C$5:$C$504,$A56,JOURNAL!$A$5:$A$504,">="&DATE(YEAR(SETUP!$B$8),MONTH(SETUP!$B$8)+11,1),JOURNAL!$A$5:$A$504,"<="&EOMONTH(SETUP!$B$8,11)) | O56: =SUM(C56:N56)
B58: CHECK — journal must balance (debits = credits) | C58: =ROUND(SUM(JOURNAL!$I$5:$I$504)-SUM(JOURNAL!$J$5:$J$504),0) | D58: Must be zero. If it is not, a journal entry is one-sided.

Sheet BUDGET
A1: BUDGET — FY1 plan. This is the TARGET half of Target vs Actuals.
A2: From the Year-1 model, restated to Oct-26 start. This is what we said we would do. TvA compares it to what we actually did.
C4: Oct-26 | D4: Nov-26 | E4: Dec-26 | F4: Jan-27 | G4: Feb-27 | H4: Mar-27 | I4: Apr-27 | J4: May-27 | K4: Jun-27 | L4: Jul-27 | M4: Aug-27 | N4: Sep-27 | O4: FY1 TOTAL
A5: NET REVENUE | C5: 71515659 | D5: 88697546 | E5: 104744328 | F5: 119797947 | G5: 133993782 | H5: 147461023 | I5: 160323021 | J5: 172697614 | K5: 184697433 | L5: 196430183 | M5: 207998913 | N5: 219502263 | O5: =SUM(C5:N5)
A6: Cost of sales | C6: 50496944 | D6: 61962807 | E6: 72074723 | F6: 80890265 | G6: 88464342 | H6: 94849354 | I6: 100095332 | J6: 104250071 | K6: 107359255 | L6: 109466568 | M6: 110613809 | N6: 110840984 | O6: =SUM(C6:N6)
A7: Jar cost expensed | C7: 8250000 | D7: 8250000 | E7: 8250000 | F7: 8250000 | G7: 8250000 | H7: 8250000 | I7: 8250000 | J7: 8250000 | K7: 8250000 | L7: 8250000 | M7: 8250000 | N7: 8250000 | O7: =SUM(C7:N7)
A8: GROSS PROFIT | C8: 12768715 | D8: 18484739 | E8: 24419605 | F8: 30657682 | G8: 37279440 | H8: 44361669 | I8: 51977689 | J8: 60197543 | K8: 69088178 | L8: 78713615 | M8: 89135104 | N8: 100411279 | O8: =SUM(C8:N8)
A9: Fixed operating costs | C9: 8163542 | D9: 8163542 | E9: 8163542 | F9: 8163542 | G9: 8163542 | H9: 8163542 | I9: 8163542 | J9: 8163542 | K9: 8163542 | L9: 8163542 | M9: 8163542 | N9: 8163542 | O9: =SUM(C9:N9)
A10: Salaries and wages | C10: 2575000 | D10: 2575000 | E10: 2575000 | F10: 2575000 | G10: 13575000 | H10: 13575000 | I10: 13575000 | J10: 13575000 | K10: 13575000 | L10: 13575000 | M10: 13575000 | N10: 13575000 | O10: =SUM(C10:N10)
A11: Transaction fees | C11: 488280 | D11: 608238 | E11: 721771 | F11: 829702 | G11: 932817 | H11: 1031864 | I11: 1127561 | J11: 1220590 | K11: 1311606 | L11: 1401232 | M11: 1490068 | N11: 1578684 | O11: =SUM(C11:N11)
A12: Depreciation | C12: 5250000 | D12: 5250000 | E12: 5250000 | F12: 5250000 | G12: 5250000 | H12: 5250000 | I12: 5250000 | J12: 5250000 | K12: 5250000 | L12: 5250000 | M12: 5250000 | N12: 5250000 | O12: =SUM(C12:N12)
A13: NET PROFIT (pre-tax) | C13: -3708107 | D13: 1887959 | E13: 7709292 | F13: 13839438 | G13: 9358081 | H13: 16341263 | I13: 23861586 | J13: 31988411 | K13: 40788030 | L13: 50323841 | M13: 60656494 | N13: 71844053 | O13: =SUM(C13:N13)
A15: Budget is fixed once FY1 starts. You do not edit a target to match an actual — that is how a company lies to itself.

Sheet P&L
A1: PROFIT OR LOSS — ACTUAL
A2: Built from JOURNAL. Revenue is stated NET of VAT and excise. Empty until trading starts 1 Oct 2026.
C4: Oct-26 | D4: Nov-26 | E4: Dec-26 | F4: Jan-27 | G4: Feb-27 | H4: Mar-27 | I4: Apr-27 | J4: May-27 | K4: Jun-27 | L4: Jul-27 | M4: Aug-27 | N4: Sep-27 | O4: FY1 TOTAL
A5: NET REVENUE | C5: =-SUM(MONTHLY!C28:C31) | D5: =-SUM(MONTHLY!D28:D31) | E5: =-SUM(MONTHLY!E28:E31) | F5: =-SUM(MONTHLY!F28:F31) | G5: =-SUM(MONTHLY!G28:G31) | H5: =-SUM(MONTHLY!H28:H31) | I5: =-SUM(MONTHLY!I28:I31) | J5: =-SUM(MONTHLY!J28:J31) | ... N5: =-SUM(MONTHLY!N28:N31) | O5: =SUM(C5:N5)
A6: Cost of sales (incl jar cost) | C6: =SUM(MONTHLY!C32:C39) | D6: =SUM(MONTHLY!D32:D39) | E6: =SUM(MONTHLY!E32:E39) | F6: =SUM(MONTHLY!F32:F39) | G6: =SUM(MONTHLY!G32:G39) | H6: =SUM(MONTHLY!H32:H39) | I6: =SUM(MONTHLY!I32:I39) | J6: =SUM(MONTHLY!J32:J39) | ... N6: =SUM(MONTHLY!N32:N39) | O6: =SUM(C6:N6)
A7: GROSS PROFIT | C7: =C5-C6 | D7: =D5-D6 | E7: =E5-E6 | F7: =F5-F6 | G7: =G5-G6 | H7: =H5-H6 | I7: =I5-I6 | J7: =J5-J6 | ... N7: =N5-N6 | O7: =SUM(C7:N7)
A8: Operating costs | C8: =SUM(MONTHLY!C40:C56) | D8: =SUM(MONTHLY!D40:D56) | E8: =SUM(MONTHLY!E40:E56) | F8: =SUM(MONTHLY!F40:F56) | G8: =SUM(MONTHLY!G40:G56) | H8: =SUM(MONTHLY!H40:H56) | I8: =SUM(MONTHLY!I40:I56) | J8: =SUM(MONTHLY!J40:J56) | ... N8: =SUM(MONTHLY!N40:N56) | O8: =SUM(C8:N8)
A9: PROFIT BEFORE TAX | C9: =C7-C8 | D9: =D7-D8 | E9: =E7-E8 | F9: =F7-F8 | G9: =G7-G8 | H9: =H7-H8 | I9: =I7-I8 | J9: =J7-J8 | ... N9: =N7-N8 | O9: =SUM(C9:N9)
A10: Corporate tax | C10: =MONTHLY!C55 | D10: =MONTHLY!D55 | E10: =MONTHLY!E55 | F10: =MONTHLY!F55 | G10: =MONTHLY!G55 | H10: =MONTHLY!H55 | I10: =MONTHLY!I55 | J10: =MONTHLY!J55 | ... N10: =MONTHLY!N55 | O10: =SUM(C10:N10)
A11: NET PROFIT | C11: =C9-C10 | D11: =D9-D10 | E11: =E9-E10 | F11: =F9-F10 | G11: =G9-G10 | H11: =H9-H10 | I11: =I9-I10 | J11: =J9-J10 | ... N11: =N9-N10 | O11: =SUM(C11:N11)
C13: Oct-26 | D13: Nov-26 | E13: Dec-26 | F13: Jan-27 | G13: Feb-27 | H13: Mar-27 | I13: Apr-27 | J13: May-27 | K13: Jun-27 | L13: Jul-27 | M13: Aug-27 | N13: Sep-27 | O13: FY1 TOTAL
A14: Gross margin | C14: =IF(C5=0,"",C7/C5) | D14: =IF(D5=0,"",D7/D5) | E14: =IF(E5=0,"",E7/E5) | F14: =IF(F5=0,"",F7/F5) | G14: =IF(G5=0,"",G7/G5) | H14: =IF(H5=0,"",H7/H5) | I14: =IF(I5=0,"",I7/I5) | J14: =IF(J5=0,"",J7/J5) | ... O14: =IF(O5=0,"",O7/O5)
A15: Pre-tax margin | C15: =IF(C5=0,"",C9/C5) | D15: =IF(D5=0,"",D9/D5) | E15: =IF(E5=0,"",E9/E5) | F15: =IF(F5=0,"",F9/F5) | G15: =IF(G5=0,"",G9/G5) | H15: =IF(H5=0,"",H9/H5) | I15: =IF(I5=0,"",I9/I5) | J15: =IF(J5=0,"",J9/J5) | ... O15: =IF(O5=0,"",O9/O5)
A16: Net margin | C16: =IF(C5=0,"",C11/C5) | D16: =IF(D5=0,"",D11/D5) | E16: =IF(E5=0,"",E11/E5) | F16: =IF(F5=0,"",F11/F5) | G16: =IF(G5=0,"",G11/G5) | H16: =IF(H5=0,"",H11/H5) | I16: =IF(I5=0,"",I11/I5) | J16: =IF(J5=0,"",J11/J5) | ... O16: =IF(O5=0,"",O11/O5)

Sheet TvA
A1: TARGET vs ACTUALS — Bucket 1. The accountable CFO.
A2: Ask "why" seven times. A gap on its own is not a finding — the reason behind it is.
A4: Reporting month (1 = Oct-26) | B4: 1
A6: Line | B6: Actual | C6: Target | D6: Variance | E6: Var % | F6: Investigate? | G6: WHY — the seventh answer
A7: Net revenue | B7: =INDEX('P&L'!$C$5:$N$5,$B$4) | C7: =INDEX(BUDGET!$C$5:$N$5,$B$4) | D7: =B7-C7 | E7: =IF(C7=0,"",D7/C7) | F7: =IF(AND(ABS(D7)>SETUP!$B$41*0+SETUP!$B$43,ABS(IFERROR(D7/C7,0))>SETUP!$B$42),"INVESTIGATE","ok")
A8: Cost of sales | B8: =INDEX('P&L'!$C$6:$N$6,$B$4) | C8: =INDEX(BUDGET!$C$6:$N$6,$B$4) | D8: =B8-C8 | E8: =IF(C8=0,"",D8/C8) | F8: =IF(AND(ABS(D8)>SETUP!$B$41*0+SETUP!$B$43,ABS(IFERROR(D8/C8,0))>SETUP!$B$42),"INVESTIGATE","ok")
A9: Gross profit | B9: =INDEX('P&L'!$C$7:$N$7,$B$4) | C9: =INDEX(BUDGET!$C$8:$N$8,$B$4) | D9: =B9-C9 | E9: =IF(C9=0,"",D9/C9) | F9: =IF(AND(ABS(D9)>SETUP!$B$41*0+SETUP!$B$43,ABS(IFERROR(D9/C9,0))>SETUP!$B$42),"INVESTIGATE","ok")
A10: Operating costs | B10: =INDEX('P&L'!$C$8:$N$8,$B$4) | C10: =INDEX(BUDGET!$C$9:$N$9,$B$4) | D10: =B10-C10 | E10: =IF(C10=0,"",D10/C10) | F10: =IF(AND(ABS(D10)>SETUP!$B$41*0+SETUP!$B$43,ABS(IFERROR(D10/C10,0))>SETUP!$B$42),"INVESTIGATE","ok")
A11: Profit before tax | B11: =INDEX('P&L'!$C$9:$N$9,$B$4) | C11: =INDEX(BUDGET!$C$13:$N$13,$B$4) | D11: =B11-C11 | E11: =IF(C11=0,"",D11/C11) | F11: =IF(AND(ABS(D11)>SETUP!$B$41*0+SETUP!$B$43,ABS(IFERROR(D11/C11,0))>SETUP!$B$42),"INVESTIGATE","ok")
A13: Threshold is set in SETUP: investigate anything more than 5% AND more than 2,000,000 UGX off target.
A14: Renew gives no materiality rule. This one is ours, and it is better than no rule.
A15: The WHY column is not optional. A variance with a blank WHY is an unfinished month.

Sheet BALANCE SHEET
A1: STATEMENT OF FINANCIAL POSITION
A2: Cumulative from JOURNAL. The CHECK row must read zero.
C4: Oct-26 | D4: Nov-26 | E4: Dec-26 | F4: Jan-27 | G4: Feb-27 | H4: Mar-27 | I4: Apr-27 | J4: May-27 | K4: Jun-27 | L4: Jul-27 | M4: Aug-27 | N4: Sep-27
A5: ASSETS
A6: Cash (bank + mobile + petty) | C6: =(SUM(MONTHLY!$C$5:C5)+SUM(MONTHLY!$C$6:C6)+SUM(MONTHLY!$C$7:C7)) | D6: =(SUM(MONTHLY!$C$5:D5)+SUM(MONTHLY!$C$6:D6)+SUM(MONTHLY!$C$7:D7)) | E6: =(SUM(MONTHLY!$C$5:E5)+SUM(MONTHLY!$C$6:E6)+SUM(MONTHLY!$C$7:E7)) | F6: =(SUM(MONTHLY!$C$5:F5)+SUM(MONTHLY!$C$6:F6)+SUM(MONTHLY!$C$7:F7)) | G6: =(SUM(MONTHLY!$C$5:G5)+SUM(MONTHLY!$C$6:G6)+SUM(MONTHLY!$C$7:G7)) | H6: =(SUM(MONTHLY!$C$5:H5)+SUM(MONTHLY!$C$6:H6)+SUM(MONTHLY!$C$7:H7)) | I6: =(SUM(MONTHLY!$C$5:I5)+SUM(MONTHLY!$C$6:I6)+SUM(MONTHLY!$C$7:I7)) | J6: =(SUM(MONTHLY!$C$5:J5)+SUM(MONTHLY!$C$6:J6)+SUM(MONTHLY!$C$7:J7)) | ... N6: =(SUM(MONTHLY!$C$5:N5)+SUM(MONTHLY!$C$6:N6)+SUM(MONTHLY!$C$7:N7))
A7: Trade receivables | C7: =(SUM(MONTHLY!$C$8:C8)) | D7: =(SUM(MONTHLY!$C$8:D8)) | E7: =(SUM(MONTHLY!$C$8:E8)) | F7: =(SUM(MONTHLY!$C$8:F8)) | G7: =(SUM(MONTHLY!$C$8:G8)) | H7: =(SUM(MONTHLY!$C$8:H8)) | I7: =(SUM(MONTHLY!$C$8:I8)) | J7: =(SUM(MONTHLY!$C$8:J8)) | ... N7: =(SUM(MONTHLY!$C$8:N8))
A8: Inventory | C8: =(SUM(MONTHLY!$C$9:C9)+SUM(MONTHLY!$C$10:C10)+SUM(MONTHLY!$C$11:C11)+SUM(MONTHLY!$C$12:C12)) | D8: =(SUM(MONTHLY!$C$9:D9)+SUM(MONTHLY!$C$10:D10)+SUM(MONTHLY!$C$11:D11)+SUM(MONTHLY!$C$12:D12)) | E8: =(SUM(MONTHLY!$C$9:E9)+SUM(MONTHLY!$C$10:E10)+SUM(MONTHLY!$C$11:E11)+SUM(MONTHLY!$C$12:E12)) | F8: =(SUM(MONTHLY!$C$9:F9)+SUM(MONTHLY!$C$10:F10)+SUM(MONTHLY!$C$11:F11)+SUM(MONTHLY!$C$12:F12)) | G8: =(SUM(MONTHLY!$C$9:G9)+SUM(MONTHLY!$C$10:G10)+SUM(MONTHLY!$C$11:G11)+SUM(MONTHLY!$C$12:G12)) | H8: =(SUM(MONTHLY!$C$9:H9)+SUM(MONTHLY!$C$10:H10)+SUM(MONTHLY!$C$11:H11)+SUM(MONTHLY!$C$12:H12)) | I8: =(SUM(MONTHLY!$C$9:I9)+SUM(MONTHLY!$C$10:I10)+SUM(MONTHLY!$C$11:I11)+SUM(MONTHLY!$C$12:I12)) | J8: =(SUM(MONTHLY!$C$9:J9)+SUM(MONTHLY!$C$10:J10)+SUM(MONTHLY!$C$11:J11)+SUM(MONTHLY!$C$12:J12)) | ... N8: =(SUM(MONTHLY!$C$9:N9)+SUM(MONTHLY!$C$10:N10)+SUM(MONTHLY!$C$11:N11)+SUM(MONTHLY!$C$12:N12))
A9: Input VAT recoverable | C9: =(SUM(MONTHLY!$C$13:C13)) | D9: =(SUM(MONTHLY!$C$13:D13)) | E9: =(SUM(MONTHLY!$C$13:E13)) | F9: =(SUM(MONTHLY!$C$13:F13)) | G9: =(SUM(MONTHLY!$C$13:G13)) | H9: =(SUM(MONTHLY!$C$13:H13)) | I9: =(SUM(MONTHLY!$C$13:I13)) | J9: =(SUM(MONTHLY!$C$13:J13)) | ... N9: =(SUM(MONTHLY!$C$13:N13))
A10: Plant and equipment (net) | C10: =(SUM(MONTHLY!$C$14:C14)+SUM(MONTHLY!$C$15:C15)) | D10: =(SUM(MONTHLY!$C$14:D14)+SUM(MONTHLY!$C$15:D15)) | E10: =(SUM(MONTHLY!$C$14:E14)+SUM(MONTHLY!$C$15:E15)) | F10: =(SUM(MONTHLY!$C$14:F14)+SUM(MONTHLY!$C$15:F15)) | G10: =(SUM(MONTHLY!$C$14:G14)+SUM(MONTHLY!$C$15:G15)) | H10: =(SUM(MONTHLY!$C$14:H14)+SUM(MONTHLY!$C$15:H15)) | I10: =(SUM(MONTHLY!$C$14:I14)+SUM(MONTHLY!$C$15:I15)) | J10: =(SUM(MONTHLY!$C$14:J14)+SUM(MONTHLY!$C$15:J15)) | ... N10: =(SUM(MONTHLY!$C$14:N14)+SUM(MONTHLY!$C$15:N15))
A11: TOTAL ASSETS | C11: =(SUM(MONTHLY!$C$5:C5)+SUM(MONTHLY!$C$6:C6)+SUM(MONTHLY!$C$7:C7)+SUM(MONTHLY!$C$8:C8)+SUM(MONTHLY!$C$9:C9)+SUM(MONTHLY!$C$10:C10)+SUM(MONTHLY!$C$11:C11)+SUM(MONTHLY!$C$12:C12)+SUM(MONTHLY!$C$13:C13)+SUM(MONTHLY!$C$14:C14)+SUM(MONTHLY!$C$15:C15)) | D11: =(SUM(MONTHLY!$C$5:D5)+SUM(MONTHLY!$C$6:D6)+SUM(MONTHLY!$C$7:D7)+SUM(MONTHLY!$C$8:D8)+SUM(MONTHLY!$C$9:D9)+SUM(MONTHLY!$C$10:D10)+SUM(MONTHLY!$C$11:D11)+SUM(MONTHLY!$C$12:D12)+SUM(MONTHLY!$C$13:D13)+SUM(MONTHLY!$C$14:D14)+SUM(MONTHLY!$C$15:D15)) | E11: =(SUM(MONTHLY!$C$5:E5)+SUM(MONTHLY!$C$6:E6)+SUM(MONTHLY!$C$7:E7)+SUM(MONTHLY!$C$8:E8)+SUM(MONTHLY!$C$9:E9)+SUM(MONTHLY!$C$10:E10)+SUM(MONTHLY!$C$11:E11)+SUM(MONTHLY!$C$12:E12)+SUM(MONTHLY!$C$13:E13)+SUM(MONTHLY!$C$14:E14)+SUM(MONTHLY!$C$15:E15)) | F11: =(SUM(MONTHLY!$C$5:F5)+SUM(MONTHLY!$C$6:F6)+SUM(MONTHLY!$C$7:F7)+SUM(MONTHLY!$C$8:F8)+SUM(MONTHLY!$C$9:F9)+SUM(MONTHLY!$C$10:F10)+SUM(MONTHLY!$C$11:F11)+SUM(MONTHLY!$C$12:F12)+SUM(MONTHLY!$C$13:F13)+SUM(MONTHLY!$C$14:F14)+SUM(MONTHLY!$C$15:F15)) | G11: =(SUM(MONTHLY!$C$5:G5)+SUM(MONTHLY!$C$6:G6)+SUM(MONTHLY!$C$7:G7)+SUM(MONTHLY!$C$8:G8)+SUM(MONTHLY!$C$9:G9)+SUM(MONTHLY!$C$10:G10)+SUM(MONTHLY!$C$11:G11)+SUM(MONTHLY!$C$12:G12)+SUM(MONTHLY!$C$13:G13)+SUM(MONTHLY!$C$14:G14)+SUM(MONTHLY!$C$15:G15)) | H11: =(SUM(MONTHLY!$C$5:H5)+SUM(MONTHLY!$C$6:H6)+SUM(MONTHLY!$C$7:H7)+SUM(MONTHLY!$C$8:H8)+SUM(MONTHLY!$C$9:H9)+SUM(MONTHLY!$C$10:H10)+SUM(MONTHLY!$C$11:H11)+SUM(MONTHLY!$C$12:H12)+SUM(MONTHLY!$C$13:H13)+SUM(MONTHLY!$C$14:H14)+SUM(MONTHLY!$C$15:H15)) | I11: =(SUM(MONTHLY!$C$5:I5)+SUM(MONTHLY!$C$6:I6)+SUM(MONTHLY!$C$7:I7)+SUM(MONTHLY!$C$8:I8)+SUM(MONTHLY!$C$9:I9)+SUM(MONTHLY!$C$10:I10)+SUM(MONTHLY!$C$11:I11)+SUM(MONTHLY!$C$12:I12)+SUM(MONTHLY!$C$13:I13)+SUM(MONTHLY!$C$14:I14)+SUM(MONTHLY!$C$15:I15)) | J11: =(SUM(MONTHLY!$C$5:J5)+SUM(MONTHLY!$C$6:J6)+SUM(MONTHLY!$C$7:J7)+SUM(MONTHLY!$C$8:J8)+SUM(MONTHLY!$C$9:J9)+SUM(MONTHLY!$C$10:J10)+SUM(MONTHLY!$C$11:J11)+SUM(MONTHLY!$C$12:J12)+SUM(MONTHLY!$C$13:J13)+SUM(MONTHLY!$C$14:J14)+SUM(MONTHLY!$C$15:J15)) | ... N11: =(SUM(MONTHLY!$C$5:N5)+SUM(MONTHLY!$C$6:N6)+SUM(MONTHLY!$C$7:N7)+SUM(MONTHLY!$C$8:N8)+SUM(MONTHLY!$C$9:N9)+SUM(MONTHLY!$C$10:N10)+SUM(MONTHLY!$C$11:N11)+SUM(MONTHLY!$C$12:N12)+SUM(MONTHLY!$C$13:N13)+SUM(MONTHLY!$C$14:N14)+SUM(MONTHLY!$C$15:N15))
A13: LIABILITIES
A14: Trade payables | C14: =-(SUM(MONTHLY!$C$16:C16)) | D14: =-(SUM(MONTHLY!$C$16:D16)) | E14: =-(SUM(MONTHLY!$C$16:E16)) | F14: =-(SUM(MONTHLY!$C$16:F16)) | G14: =-(SUM(MONTHLY!$C$16:G16)) | H14: =-(SUM(MONTHLY!$C$16:H16)) | I14: =-(SUM(MONTHLY!$C$16:I16)) | J14: =-(SUM(MONTHLY!$C$16:J16)) | ... N14: =-(SUM(MONTHLY!$C$16:N16))
A15: CUSTOMER DEPOSITS — refundable | C15: =-(SUM(MONTHLY!$C$17:C17)) | D15: =-(SUM(MONTHLY!$C$17:D17)) | E15: =-(SUM(MONTHLY!$C$17:E17)) | F15: =-(SUM(MONTHLY!$C$17:F17)) | G15: =-(SUM(MONTHLY!$C$17:G17)) | H15: =-(SUM(MONTHLY!$C$17:H17)) | I15: =-(SUM(MONTHLY!$C$17:I17)) | J15: =-(SUM(MONTHLY!$C$17:J17)) | ... N15: =-(SUM(MONTHLY!$C$17:N17))
A16: URA — VAT, excise, stamps | C16: =-(SUM(MONTHLY!$C$18:C18)+SUM(MONTHLY!$C$19:C19)+SUM(MONTHLY!$C$20:C20)) | D16: =-(SUM(MONTHLY!$C$18:D18)+SUM(MONTHLY!$C$19:D19)+SUM(MONTHLY!$C$20:D20)) | E16: =-(SUM(MONTHLY!$C$18:E18)+SUM(MONTHLY!$C$19:E19)+SUM(MONTHLY!$C$20:E20)) | F16: =-(SUM(MONTHLY!$C$18:F18)+SUM(MONTHLY!$C$19:F19)+SUM(MONTHLY!$C$20:F20)) | G16: =-(SUM(MONTHLY!$C$18:G18)+SUM(MONTHLY!$C$19:G19)+SUM(MONTHLY!$C$20:G20)) | H16: =-(SUM(MONTHLY!$C$18:H18)+SUM(MONTHLY!$C$19:H19)+SUM(MONTHLY!$C$20:H20)) | I16: =-(SUM(MONTHLY!$C$18:I18)+SUM(MONTHLY!$C$19:I19)+SUM(MONTHLY!$C$20:I20)) | J16: =-(SUM(MONTHLY!$C$18:J18)+SUM(MONTHLY!$C$19:J19)+SUM(MONTHLY!$C$20:J20)) | ... N16: =-(SUM(MONTHLY!$C$18:N18)+SUM(MONTHLY!$C$19:N19)+SUM(MONTHLY!$C$20:N20))
A17: Payroll statutory (PAYE, NSSF, LST) | C17: =-(SUM(MONTHLY!$C$21:C21)+SUM(MONTHLY!$C$22:C22)+SUM(MONTHLY!$C$23:C23)) | D17: =-(SUM(MONTHLY!$C$21:D21)+SUM(MONTHLY!$C$22:D22)+SUM(MONTHLY!$C$23:D23)) | E17: =-(SUM(MONTHLY!$C$21:E21)+SUM(MONTHLY!$C$22:E22)+SUM(MONTHLY!$C$23:E23)) | F17: =-(SUM(MONTHLY!$C$21:F21)+SUM(MONTHLY!$C$22:F22)+SUM(MONTHLY!$C$23:F23)) | G17: =-(SUM(MONTHLY!$C$21:G21)+SUM(MONTHLY!$C$22:G22)+SUM(MONTHLY!$C$23:G23)) | H17: =-(SUM(MONTHLY!$C$21:H21)+SUM(MONTHLY!$C$22:H22)+SUM(MONTHLY!$C$23:H23)) | I17: =-(SUM(MONTHLY!$C$21:I21)+SUM(MONTHLY!$C$22:I22)+SUM(MONTHLY!$C$23:I23)) | J17: =-(SUM(MONTHLY!$C$21:J21)+SUM(MONTHLY!$C$22:J22)+SUM(MONTHLY!$C$23:J23)) | ... N17: =-(SUM(MONTHLY!$C$21:N21)+SUM(MONTHLY!$C$22:N22)+SUM(MONTHLY!$C$23:N23))
A18: Corporate tax payable | C18: =-(SUM(MONTHLY!$C$24:C24)) | D18: =-(SUM(MONTHLY!$C$24:D24)) | E18: =-(SUM(MONTHLY!$C$24:E24)) | F18: =-(SUM(MONTHLY!$C$24:F24)) | G18: =-(SUM(MONTHLY!$C$24:G24)) | H18: =-(SUM(MONTHLY!$C$24:H24)) | I18: =-(SUM(MONTHLY!$C$24:I24)) | J18: =-(SUM(MONTHLY!$C$24:J24)) | ... N18: =-(SUM(MONTHLY!$C$24:N24))
A19: Loans and borrowings | C19: =-(SUM(MONTHLY!$C$25:C25)) | D19: =-(SUM(MONTHLY!$C$25:D25)) | E19: =-(SUM(MONTHLY!$C$25:E25)) | F19: =-(SUM(MONTHLY!$C$25:F25)) | G19: =-(SUM(MONTHLY!$C$25:G25)) | H19: =-(SUM(MONTHLY!$C$25:H25)) | I19: =-(SUM(MONTHLY!$C$25:I25)) | J19: =-(SUM(MONTHLY!$C$25:J25)) | ... N19: =-(SUM(MONTHLY!$C$25:N25))
A20: TOTAL LIABILITIES | C20: =-(SUM(MONTHLY!$C$16:C16)+SUM(MONTHLY!$C$17:C17)+SUM(MONTHLY!$C$18:C18)+SUM(MONTHLY!$C$19:C19)+SUM(MONTHLY!$C$20:C20)+SUM(MONTHLY!$C$21:C21)+SUM(MONTHLY!$C$22:C22)+SUM(MONTHLY!$C$23:C23)+SUM(MONTHLY!$C$24:C24)+SUM(MONTHLY!$C$25:C25)) | D20: =-(SUM(MONTHLY!$C$16:D16)+SUM(MONTHLY!$C$17:D17)+SUM(MONTHLY!$C$18:D18)+SUM(MONTHLY!$C$19:D19)+SUM(MONTHLY!$C$20:D20)+SUM(MONTHLY!$C$21:D21)+SUM(MONTHLY!$C$22:D22)+SUM(MONTHLY!$C$23:D23)+SUM(MONTHLY!$C$24:D24)+SUM(MONTHLY!$C$25:D25)) | E20: =-(SUM(MONTHLY!$C$16:E16)+SUM(MONTHLY!$C$17:E17)+SUM(MONTHLY!$C$18:E18)+SUM(MONTHLY!$C$19:E19)+SUM(MONTHLY!$C$20:E20)+SUM(MONTHLY!$C$21:E21)+SUM(MONTHLY!$C$22:E22)+SUM(MONTHLY!$C$23:E23)+SUM(MONTHLY!$C$24:E24)+SUM(MONTHLY!$C$25:E25)) | F20: =-(SUM(MONTHLY!$C$16:F16)+SUM(MONTHLY!$C$17:F17)+SUM(MONTHLY!$C$18:F18)+SUM(MONTHLY!$C$19:F19)+SUM(MONTHLY!$C$20:F20)+SUM(MONTHLY!$C$21:F21)+SUM(MONTHLY!$C$22:F22)+SUM(MONTHLY!$C$23:F23)+SUM(MONTHLY!$C$24:F24)+SUM(MONTHLY!$C$25:F25)) | G20: =-(SUM(MONTHLY!$C$16:G16)+SUM(MONTHLY!$C$17:G17)+SUM(MONTHLY!$C$18:G18)+SUM(MONTHLY!$C$19:G19)+SUM(MONTHLY!$C$20:G20)+SUM(MONTHLY!$C$21:G21)+SUM(MONTHLY!$C$22:G22)+SUM(MONTHLY!$C$23:G23)+SUM(MONTHLY!$C$24:G24)+SUM(MONTHLY!$C$25:G25)) | H20: =-(SUM(MONTHLY!$C$16:H16)+SUM(MONTHLY!$C$17:H17)+SUM(MONTHLY!$C$18:H18)+SUM(MONTHLY!$C$19:H19)+SUM(MONTHLY!$C$20:H20)+SUM(MONTHLY!$C$21:H21)+SUM(MONTHLY!$C$22:H22)+SUM(MONTHLY!$C$23:H23)+SUM(MONTHLY!$C$24:H24)+SUM(MONTHLY!$C$25:H25)) | I20: =-(SUM(MONTHLY!$C$16:I16)+SUM(MONTHLY!$C$17:I17)+SUM(MONTHLY!$C$18:I18)+SUM(MONTHLY!$C$19:I19)+SUM(MONTHLY!$C$20:I20)+SUM(MONTHLY!$C$21:I21)+SUM(MONTHLY!$C$22:I22)+SUM(MONTHLY!$C$23:I23)+SUM(MONTHLY!$C$24:I24)+SUM(MONTHLY!$C$25:I25)) | J20: =-(SUM(MONTHLY!$C$16:J16)+SUM(MONTHLY!$C$17:J17)+SUM(MONTHLY!$C$18:J18)+SUM(MONTHLY!$C$19:J19)+SUM(MONTHLY!$C$20:J20)+SUM(MONTHLY!$C$21:J21)+SUM(MONTHLY!$C$22:J22)+SUM(MONTHLY!$C$23:J23)+SUM(MONTHLY!$C$24:J24)+SUM(MONTHLY!$C$25:J25)) | ... N20: =-(SUM(MONTHLY!$C$16:N16)+SUM(MONTHLY!$C$17:N17)+SUM(MONTHLY!$C$18:N18)+SUM(MONTHLY!$C$19:N19)+SUM(MONTHLY!$C$20:N20)+SUM(MONTHLY!$C$21:N21)+SUM(MONTHLY!$C$22:N22)+SUM(MONTHLY!$C$23:N23)+SUM(MONTHLY!$C$24:N24)+SUM(MONTHLY!$C$25:N25))
A22: EQUITY
A23: Share capital | C23: =-(SUM(MONTHLY!$C$26:C26)) | D23: =-(SUM(MONTHLY!$C$26:D26)) | E23: =-(SUM(MONTHLY!$C$26:E26)) | F23: =-(SUM(MONTHLY!$C$26:F26)) | G23: =-(SUM(MONTHLY!$C$26:G26)) | H23: =-(SUM(MONTHLY!$C$26:H26)) | I23: =-(SUM(MONTHLY!$C$26:I26)) | J23: =-(SUM(MONTHLY!$C$26:J26)) | ... N23: =-(SUM(MONTHLY!$C$26:N26))
A24: Retained earnings (incl. current-year profit) | C24: =-(SUM(MONTHLY!$C$27:C27))+SUM('P&L'!$C$11:C11) | D24: =-(SUM(MONTHLY!$C$27:D27))+SUM('P&L'!$C$11:D11) | E24: =-(SUM(MONTHLY!$C$27:E27))+SUM('P&L'!$C$11:E11) | F24: =-(SUM(MONTHLY!$C$27:F27))+SUM('P&L'!$C$11:F11) | G24: =-(SUM(MONTHLY!$C$27:G27))+SUM('P&L'!$C$11:G11) | H24: =-(SUM(MONTHLY!$C$27:H27))+SUM('P&L'!$C$11:H11) | I24: =-(SUM(MONTHLY!$C$27:I27))+SUM('P&L'!$C$11:I11) | J24: =-(SUM(MONTHLY!$C$27:J27))+SUM('P&L'!$C$11:J11) | ... N24: =-(SUM(MONTHLY!$C$27:N27))+SUM('P&L'!$C$11:N11)
A25: TOTAL EQUITY | C25: =C23+C24 | D25: =D23+D24 | E25: =E23+E24 | F25: =F23+F24 | G25: =G23+G24 | H25: =H23+H24 | I25: =I23+I24 | J25: =J23+J24 | ... N25: =N23+N24
A27: CHECK — must be zero | C27: =ROUND(C11-C20-C25,0) | D27: =ROUND(D11-D20-D25,0) | E27: =ROUND(E11-E20-E25,0) | F27: =ROUND(F11-F20-F25,0) | G27: =ROUND(G11-G20-G25,0) | H27: =ROUND(H11-H20-H25,0) | I27: =ROUND(I11-I20-I25,0) | J27: =ROUND(J11-J20-J25,0) | ... N27: =ROUND(N11-N20-N25,0)
A29: CASH GENUINELY OURS | C29: =C6-C15 | D29: =D6-D15 | E29: =E6-E15 | F29: =F6-F15 | G29: =G6-G15 | H29: =H6-H15 | I29: =I6-I15 | J29: =J6-J15 | ... N29: =N6-N15
A30: Cash less customer deposits. Manage to THIS line, never to the cash line.

Sheet VIEW · CO-FOUNDERS
A1: CO-FOUNDERS
A2: READER: The people who carry the risk with you
A3: THEY ARE GRADING YOU ON: Honesty. They can handle bad news; they cannot handle finding out late.
A4: The unvarnished version. Everything that is wrong goes here first, before it goes anywhere else.
A6: WHERE WE ACTUALLY STAND
A7: Cash in the bank | B7: =INDEX('BALANCE SHEET'!$C$6:$N$6,TvA!$B$4) | D7: Includes money that is not ours
A8: Customer deposits we owe back | B8: =INDEX('BALANCE SHEET'!$C$15:$N$15,TvA!$B$4) | D8: Repayable when a jar comes back
A9: CASH GENUINELY OURS | B9: =INDEX('BALANCE SHEET'!$C$29:$N$29,TvA!$B$4) | D9: This is the real number. Manage to it.
A10: Months of cover at current burn | B10: =IFERROR(B8/MAX(1,-INDEX('P&L'!$C$11:$N$11,TvA!$B$4)),"n/a") | D10: Blank while profitable
A11: Profit before tax this month | B11: =INDEX('P&L'!$C$9:$N$9,TvA!$B$4)
A12: Against target | B12: =TvA!D12 | D12: Variance on profit before tax
A14: THE THINGS WE ARE CARRYING
A15: • No facility, no overdraft, no committed tranche behind the thinnest month.
A16: • Half the B2B price ladder is still unapproved, so part of the revenue mix is assumption.
A17: • We model zero jar returns. Every jar that comes back is cash out with no revenue against it.
A18: • We model zero receivables. The first institution asking for 30 days changes the cash shape.
A19: • NSSF employer is recorded at 5%; statutory is 10%. Local Service Tax is missing entirely.
A20: • Finance is two founders wearing hats. Segregation of duties is arithmetically impossible.
A22: THE MONTHLY MESSAGE — LEAD
A23: L — the finding | B23: [one sentence: what happened and what I recommend]
A24: E — the driver | B24: [the driver — the seventh answer, not the first]
A25: A — the amount | B25: [the amount at stake, in UGX]
A26: D — the decision | B26: [what I need decided, and by when]

Sheet VIEW · INVESTORS
A1: INVESTORS
A2: READER: Existing and prospective equity investors
A3: THEY ARE GRADING YOU ON: "Growth, and no surprises." — Renew CFO100 Session 4
A4: Growth trajectory, unit economics, and the risks named BEFORE they are asked about. Never let an investor discover a problem you knew about.
A6: THE HEADLINE
A7: Net revenue — month | B7: =INDEX('P&L'!$C$5:$N$5,TvA!$B$4)
A8: Net revenue — year to date | B8: =SUM(OFFSET('P&L'!$C$5,0,0,1,TvA!$B$4))
A9: Gross margin | B9: =IFERROR(INDEX('P&L'!$C$7:$N$7,TvA!$B$4)/INDEX('P&L'!$C$5:$N$5,TvA!$B$4),"") | D9: Plan: 18% in M1 rising to 46% by M12
A10: Pre-tax margin | B10: =IFERROR(INDEX('P&L'!$C$9:$N$9,TvA!$B$4)/INDEX('P&L'!$C$5:$N$5,TvA!$B$4),"") | D10: Renew band: 5% life support, 10% floor, 15% healthy
A11: Revenue vs target | B11: =TvA!E8 | D11: Bucket 1. The number they will ask about.
A13: UNIT ECONOMICS — the thing that actually decides this business
A14: Jars sold per day (month average) | D14: From JOURNAL once trading
A15: Full break-even, incl jar programme | B15: 577 | D15: jars/day in month 1 — from the plan
A16: Headroom over break-even | D16: Negative means we are below break-even
A17: Contribution per unit | D17: Plan: 1,617 in M1 rising to 2,090 by M12
A18: Customer acquisition cost per jar customer | D18: GAP-18 — NOT MODELLED. They will ask.
A20: RISKS WE ARE NAMING OURSELVES
A21: • Pre-revenue until 1 Oct 2026. Every ratio before that date is a forecast, not a result.
A22: • Single site, single city. Any interruption is total, not partial.
A23: • Customer deposits are our largest liability and are funded by growth.
A24: • The volume ramp is not yet contracted. It is the assumption the whole plan rests on.
A25: • No auditor appointed. Reviewed accounts are cheaper now than under a raise deadline.
A27: THE MONTHLY MESSAGE — LEAD
A28: L — the finding | B28: [the finding — growth, and the one thing that could derail it]
A29: E — the driver | B29: [the driver]
A30: A — the amount | B30: [UGX, and what it means for the plan]
A31: D — the decision | B31: [what we are asking for, or 'nothing needed from you']
A33: Renew: "Nothing needed from you" is a legitimate D line. Use it when it is true.

Sheet VIEW · INTERNAL
A1: INTERNAL — MANAGEMENT
A2: READER: Sammy and whoever runs the plant and the route
A3: THEY ARE GRADING YOU ON: "Accuracy, and can I use this Monday morning." — Renew CFO100 Session 4
A4: Operational. No ratios nobody acts on. Only numbers that change what someone does this week.
A6: THIS WEEK
A7: Jars/day needed to break even (incl jar programme) | B7: 577 | D7: The number everyone on site should know
A8: Jars/day actually produced
A9: Above / (below) break-even
A10: Cash at close of last week | D10: From CASH 13-WEEK
A11: Headroom over the minimum floor | D11: Negative = something gets cut this week
A13: MIX AND COST
A14: Volume — 20L refill | D14: From JOURNAL, by Product
A15: Volume — 20L single-use | D15: From JOURNAL, by Product
A16: Volume — 5L single-use | D16: From JOURNAL, by Product
A17: New jars issued | D17: From JOURNAL, by Product
A18: Jars returned | D18: From JOURNAL, by Product
A19: Cost of sales per unit | D19: Plan: 3,884 in M1 falling to 2,132 by M12
A20: Days of inventory on hand | D20: Plan: about 3 days
A22: THE WEEKLY FLASH — one page, every week
A23: • Expected month-end revenue
A24: • Expected month-end contribution
A25: • Expected month-end cash
A26: • Anything that will miss, and what I am doing about it

Sheet VIEW · TAX (URA)
A1: TAX — URA
A2: READER: Uganda Revenue Authority, and our tax advisor
A3: THEY ARE GRADING YOU ON: "Is the format right and the number defensible." — Renew CFO100 Session 4
A4: Nothing persuasive here. Only what is owed, what was paid, and when it is due. Every figure must trace to a journal entry.
A6: COLLECTED FOR URA — never our revenue
A7: Gross billings (VAT-inclusive) | D7: Memo line only
A8: Output VAT | B8: =-INDEX('BALANCE SHEET'!$C$16:$N$16,TvA!$B$4)*0+SUM(OFFSET(MONTHLY!$C$18,0,0,1,TvA!$B$4))*-1 | D8: 18%
A9: Excise duty | B9: =SUM(OFFSET(MONTHLY!$C$19,0,0,1,TvA!$B$4))*-1 | D9: Higher of 10% ad valorem or 50 UGX/litre
A10: Digital tax stamps | B10: =SUM(OFFSET(MONTHLY!$C$20,0,0,1,TvA!$B$4))*-1 | D10: 15 UGX per unit, refills included
A11: Input VAT recoverable | B11: =SUM(OFFSET(MONTHLY!$C$13,0,0,1,TvA!$B$4)) | D11: Only as good as our EFRIS discipline
A13: PAYROLL STATUTORY
A14: PAYE withheld | B14: =SUM(OFFSET(MONTHLY!$C$21,0,0,1,TvA!$B$4))*-1
A15: NSSF — employee 5%
A16: NSSF — employer | D16: GAP-04: recorded 5%, statutory 10%. CONFIRM before payroll runs.
A17: Local Service Tax | D17: GAP-05: NOT IN THE MODEL AT ALL
A19: CORPORATE TAX
A20: Accrued year to date | B20: =SUM(OFFSET('P&L'!$C$10,0,0,1,TvA!$B$4))
A21: Paid year to date
A22: Payable | B22: =-INDEX('BALANCE SHEET'!$C$18:$N$18,TvA!$B$4)*-1 | D22: Accrues monthly, PAID QUARTERLY
A24: FILING CALENDAR — fix a date each month and never move it
A25: VAT return | B25: 15th of the following month
A26: PAYE and NSSF | B26: 15th of the following month
A27: Corporate tax (provisional) | B27: Quarterly
A28: Trading licence (KCCA) | B28: Annual — 600,000
A29: Local Service Tax | B29: GAP-05 — confirm the cycle
A30: Annual return | B30: Annual
A32: 29.1% of gross billings is VAT and excise. None of it is ours. Do not spend it.

Sheet VIEW · LENDERS
A1: LENDERS AND PARTNERS
A2: READER: Banks, DFIs, catalytic funders, trade partners
A3: THEY ARE GRADING YOU ON: "Can this business pay what it owes." — Renew CFO100 Session 4
A4: Capacity to service, not growth story. A lender is underwriting the downside, so show them you have one.
A6: CAPACITY TO SERVICE
A7: EBITDA year to date | B7: =SUM(OFFSET('P&L'!$C$9,0,0,1,TvA!$B$4))+SUM(OFFSET(MONTHLY!$C$54,0,0,1,TvA!$B$4)) | D7: Profit before tax plus depreciation
A8: Total debt | B8: =-INDEX('BALANCE SHEET'!$C$19:$N$19,TvA!$B$4)*-1 | D8: None today — self-funded
A9: Debt to EBITDA | D9: Target under 3.0x
A10: DSCR | D10: EBITDA / debt service
A11: Indicative debt capacity | B11: 400000 | D11: USD, at 1.25x cover — from the model, Site 1 only
A13: LIQUIDITY AND THE DOWNSIDE
A14: Cash genuinely ours | B14: =INDEX('BALANCE SHEET'!$C$29:$N$29,TvA!$B$4) | D14: Excludes refundable deposits
A15: Minimum cash floor (policy) | B15: =SETUP!$B$41
A16: Lowest projected cash point | B16: 17548449 | D16: Month 1 of the plan. No facility behind it.
A17: Cash conversion cycle | D17: Plan: 3 days. Inventory only.
A19: WHAT WE WOULD PLEDGE, AND WHAT WE WOULD NOT
A20: Plant and equipment at cost | B20: 315000000
A21: Customer deposits — NOT available as security | B21: =INDEX('BALANCE SHEET'!$C$15:$N$15,TvA!$B$4) | D21: It is customers' money. Never offer it as headroom.
A23: A lender will ask what happens at 60% of plan. The answer lives in the one-site model's scenario cell — bring it, do not wait to be asked.

Sheet VIEW · GROWTH
A1: GROWTH
A2: READER: Sammy, co-founders, and anyone funding the next site
A3: THEY ARE GRADING YOU ON: Whether the next step is earned or merely wanted
A4: Renew's structural question: is the hiring step-up plus the expansion affordable given the ramp? The fix here is not a timing trick — it is a decision about pace.
A6: IS SITE 1 EARNING THE RIGHT TO A SITE 2?
A7: Capacity utilisation | D7: Actual jars/day against 2,000/day capacity
A8: Months at or above full break-even | D8: Renew would want several consecutive
A9: Cash genuinely ours | B9: =INDEX('BALANCE SHEET'!$C$29:$N$29,TvA!$B$4) | D9: The only cash that can fund anything
A10: Gross margin trend | D10: Plan: rising every month as mix shifts to refill
A12: THE CUSTOMER ENGINE — mostly unmeasured, and that is the problem
A13: New jar customers this month | D13: Plan assumes 750 every month, flat, forever
A14: Jar customers lost (churn) | D14: GAP-20 — NOT MODELLED
A15: Cost to acquire one jar customer | D15: GAP-18 — NOT MODELLED. No marketing line exists.
A16: Revenue per jar customer per month
A17: Lifetime value per jar customer | D17: Needs churn first
A19: THE DECISION GATES
A20: AP/AR clerk | B20: 650 jars/day — pays for itself on input VAT recovery alone
A21: Accounting / Finance Manager | B21: 950 jars/day
A22: GL Accountant | B22: 1,400 jars/day
A23: Financial Controller | B23: Site 2 committed
A24: CFO as a real seat | B24: Site 3, or a raise closed — when there is a board and a cap table to serve
A26: The hiring step at month 5 costs 72,600,000 UGX of cash over thirteen months. Toggle it in the one-site model and read the difference before committing.

Sheet ACCESS
A1: ACCESS — who runs it, who sees what
A2: Renew best practice #2: group users of financial reports by role. It protects data privacy and keeps one version of the truth.
A4: Who | B4: Access level | C4: Sees | D4: Notes
A5: Sammy (founder / acting CFO) | B5: OWNER — edit all | C5: Everything | D5: Runs it. Owns the close, the Monday forecast and every view.
A6: Co-founder(s) | B6: Edit | C6: Everything | D6: Same visibility as the CFO. No filtered version between founders.
A7: AP/AR clerk (from 650 jars/day) | B7: Edit JOURNAL only | C7: JOURNAL, COST BOOK | D7: Daily entry. Cannot change SETUP, BUDGET or any view.
A8: Accountant / bookkeeper | B8: Edit JOURNAL + COA | C8: Input layer, P&L, BS | D8: Second pair of eyes. Our only real compensating control.
A9: Auditor (once appointed) | B9: Comment | C9: Everything | D9: GAP-17 — not appointed yet
A10: Investors | B10: VIEW ONLY link | C10: VIEW · INVESTORS | D10: Never share the whole file. Share the view.
A11: Lenders / partners | B11: VIEW ONLY link | C11: VIEW · LENDERS | D11: Same rule.
A12: Tax advisor / URA | B12: VIEW ONLY link | C12: VIEW · TAX (URA) | D12: Plus source documents on request.
A13: Plant and route staff | B13: VIEW ONLY link | C13: VIEW · INTERNAL | D13: The break-even number should be on the wall.
A15: THE RULE: outsiders get a link to ONE TAB, never to the file.
A16: In Google Sheets: File > Share > publish or share a single sheet, or copy the view into a separate shared file that pulls from here with IMPORTRANGE.
A17: Nobody edits a view. If a view is wrong, the JOURNAL is wrong — fix it there.
A18: One person owns the close. Today that is Sammy. When the AP/AR clerk arrives, entry moves; ownership does not.

Sheet CASH 13-WEEK
A1: 13-WEEK ROLLING CASH FORECAST
A2: THE STANDING RULE: every Monday morning once we are selling, roll this forward one week and type what you actually expect. Then read the ALARM row.
A4: Week commencing | C4: =SETUP!$B$8+0 | D4: =SETUP!$B$8+7 | E4: =SETUP!$B$8+14 | F4: =SETUP!$B$8+21 | G4: =SETUP!$B$8+28 | H4: =SETUP!$B$8+35 | I4: =SETUP!$B$8+42 | J4: =SETUP!$B$8+49 | K4: =SETUP!$B$8+56 | L4: =SETUP!$B$8+63 | M4: =SETUP!$B$8+70 | N4: =SETUP!$B$8+77 | O4: =SETUP!$B$8+84 | P4: 13-WK TOTAL
A5: OPENING CASH | C5: =SETUP!$B$28 | D5: =C25 | E5: =D25 | F5: =E25 | G5: =F25 | H5: =G25 | I5: =H25 | J5: =I25 | K5: =J25 | ... O5: =N25
A6: RECEIPTS
A7: Cash sales — refill and single-use | P7: =SUM(C7:O7)
A8: Jar deposits received | P8: =SUM(C8:O8)
A9: Input VAT refunds from URA | P9: =SUM(C9:O9)
A10: Other receipts / financing | P10: =SUM(C10:O10)
A11: TOTAL RECEIPTS | C11: =SUM(C7:C10) | D11: =SUM(D7:D10) | E11: =SUM(E7:E10) | F11: =SUM(F7:F10) | G11: =SUM(G7:G10) | H11: =SUM(H7:H10) | I11: =SUM(I7:I10) | J11: =SUM(J7:J10) | ... O11: =SUM(O7:O10) | P11: =SUM(C11:O11)
A12: PAYMENTS
A13: Raw materials and packaging | P13: =SUM(C13:O13)
A14: Jar purchases | P14: =SUM(C14:O14)
A15: Salaries, PAYE and NSSF | P15: =SUM(C15:O15)
A16: Rent, power, security, other overheads | P16: =SUM(C16:O16)
A17: Delivery and fuel | P17: =SUM(C17:O17)
A18: URA — VAT and excise | P18: =SUM(C18:O18)
A19: URA — corporate tax | P19: =SUM(C19:O19)
A20: Jar deposit REFUNDS | P20: =SUM(C20:O20)
A21: Capex and other | P21: =SUM(C21:O21)
A22: TOTAL PAYMENTS | C22: =SUM(C13:C21) | D22: =SUM(D13:D21) | E22: =SUM(E13:E21) | F22: =SUM(F13:F21) | G22: =SUM(G13:G21) | H22: =SUM(H13:H21) | I22: =SUM(I13:I21) | J22: =SUM(J13:J21) | ... O22: =SUM(O13:O21) | P22: =SUM(C22:O22)
A24: NET MOVEMENT | C24: =C11-C22 | D24: =D11-D22 | E24: =E11-E22 | F24: =F11-F22 | G24: =G11-G22 | H24: =H11-H22 | I24: =I11-I22 | J24: =J11-J22 | ... O24: =O11-O22 | P24: =SUM(C24:O24)
A25: CLOSING CASH | C25: =C5+C24 | D25: =D5+D24 | E25: =E5+E24 | F25: =F5+F24 | G25: =G5+G24 | H25: =H5+H24 | I25: =I5+I24 | J25: =J5+J24 | ... O25: =O5+O24
A26: Minimum cash floor | C26: =SETUP!$B$41 | D26: =SETUP!$B$41 | E26: =SETUP!$B$41 | F26: =SETUP!$B$41 | G26: =SETUP!$B$41 | H26: =SETUP!$B$41 | I26: =SETUP!$B$41 | J26: =SETUP!$B$41 | ... O26: =SETUP!$B$41
A27: HEADROOM | C27: =C25-C26 | D27: =D25-D26 | E27: =E25-E26 | F27: =F25-F26 | G27: =G25-G26 | H27: =H25-H26 | I27: =I25-I26 | J27: =J25-J26 | ... O27: =O25-O26
A28: ALARM | C28: =IF(C25<C26,"BREACH","ok") | D28: =IF(D25<D26,"BREACH","ok") | E28: =IF(E25<E26,"BREACH","ok") | F28: =IF(F25<F26,"BREACH","ok") | G28: =IF(G25<G26,"BREACH","ok") | H28: =IF(H25<H26,"BREACH","ok") | I28: =IF(I25<I26,"BREACH","ok") | J28: =IF(J25<J26,"BREACH","ok") | ... O28: =IF(O25<O26,"BREACH","ok")
A30: Renew, Session 4, on the weekly cash meeting: 'Review the end cash position with the forecast. Any difference? Any payments we need to slow or receipts we need to accelerate?'
A31: Their Accounting and Finance Team Checklist puts this on the Finance Manager as a WEEKLY duty.
A32: Jar deposits received are NOT revenue. They are here because they are cash, and this tab is about cash.
A33: Jar deposit REFUNDS is a row on purpose. It is zero today and it will not stay zero.

Sheet GAPS
A1: GAPS — what we do not know, who answers it, and by when
A2: Nothing in this workbook is guessed silently. Every unknown is here with a name against it. Blockers must clear BEFORE 1 October.
A4: ID | B4: What we need | C4: Blocks | D4: Owner | E4: Due | F4: Why it matters
A5: GAP-01 | B5: URA TIN | C5: Every filing | D5: Sammy | E5: Before 1 Oct | F5: Cannot file anything without it
A6: GAP-02 | B6: VAT registered? From what date? | C6: Pricing and every invoice | D6: Sammy | E6: BEFORE 1 OCT | F6: If not registered, we charge no output VAT and recover no input VAT. Changes price, margin and cash from day one.
A7: GAP-03 | B7: EFRIS enrolled? | C7: Input VAT recovery | D7: Sammy | E7: BEFORE 1 OCT | F7: The 75% recovery assumption is worth ~39.5m/yr and is EARNED by EFRIS invoices. No EFRIS, no recovery.
A8: GAP-04 | B8: NSSF EMPLOYER rate — 5% or 10%? | C8: Payroll, P&L, cash | D8: Sammy | E8: BEFORE first payroll | F8: Model says 5%, statutory is 10%. On 118.9m of wages this is material and it understates cost.
A9: GAP-05 | B9: Local Service Tax — rate and cycle | C9: Payroll | D9: Sammy | E9: BEFORE first payroll | F9: Absent from the model entirely
A10: GAP-06 | B10: UNBS certification — status and date | C10: Whether we can sell at all | D10: Sammy | E10: BEFORE 1 OCT | F10: A delay pushes the whole ramp right and turns a one-month loss into a one-quarter loss
A11: GAP-07 | B11: Opening cash at 1 Oct — bank, mobile, petty | C11: Everything | D11: Sammy | E11: 30 Sep | F11: The model assumes 4,000,000. Count it, do not assume it.
A12: GAP-08 | B12: Opening inventory at 1 Oct — physical count | C12: Balance sheet, COGS | D12: Sammy | E12: 30 Sep | F12: Model assumes 5,112,500
A13: GAP-09 | B13: Jars already in the field, deposits already held | C13: Deposit liability | D13: Sammy | E13: 30 Sep | F13: If any jars are out there, we already owe that money back
A14: GAP-10 | B14: Opening receivables, payables, loans | C14: Balance sheet | D14: Sammy | E14: 30 Sep | F14: Model assumes all three are zero
A15: GAP-11 | B15: Plant life and membrane replacement schedule | C15: Depreciation, capex | D15: Sammy | E15: Oct | F15: Zero maintenance capex in a full year of 2,000 jars/day cannot be right
... A26: GAP-22 | B26: Who else gets edit access, and when | C26: Controls | D26: Sammy | E26: Oct | F26: Today it is one person, which means no segregation of duties
B28: Highlighted rows block the 1 October start. Everything else can follow in October.
B30: Renew, Session 2: "I don't know yet. I will have that by Thursday at noon." Admit, commit to a time, deliver. Bluffing is fatal.

Sheet CHECKS
A1: CHECKS — run these before anything leaves this file
A3: Check | B3: Value | C3: Should be | D3: Verdict
A4: Journal balances (debits = credits) | B4: =MONTHLY!C58 | C4: 0 | D4: =IF(B4=0,"OK","FIX THIS FIRST")
A5: Balance sheet balances (month 1) | B5: ='BALANCE SHEET'!C27 | C5: 0 | D5: =IF(B5=0,"OK","FIX THIS FIRST")
A6: Balance sheet balances (month 12) | B6: ='BALANCE SHEET'!N27 | C6: 0 | D6: =IF(B6=0,"OK","FIX THIS FIRST")
A7: Journal rows with no account code | B7: =COUNTIFS(JOURNAL!$A$5:$A$504,"<>",JOURNAL!$C$5:$C$504,"") | C7: 0 | D7: =IF(B7=0,"OK","FIX THIS FIRST")
A8: Journal rows with neither debit nor credit | B8: =COUNTIFS(JOURNAL!$A$5:$A$504,"<>",JOURNAL!$I$5:$I$504,0,JOURNAL!$J$5:$J$504,0) | C8: 0 | D8: =IF(B8=0,"OK","FIX THIS FIRST")
A9: Gaps still blocking the 1 Oct start | B9: =COUNTIF(GAPS!E:E,"BEFORE 1 OCT")+COUNTIF(GAPS!E:E,"30 Sep")+COUNTIF(GAPS!E:E,"BEFORE first payroll") | C9: 0 by 1 Oct | D9: =IF(B9=0,"OK","FIX THIS FIRST")
A11: Renew's pre-send checklist, Session 4:
A12: Can I trust this data? Does it cover what actually matters? Is it still timely?
A13: Is it clear enough to digest in under a minute?
A14: If the answer to any of those is no, it isn't ready.
A16: Renew's pre-send integrity checklist, Session 2 — BEFORE SENDING THE FS TO THE CEO:
A17: cash check, net income check, receivables, payables, inventory, non-cash expense, interest, unusual variance.

Sheet REQUEST REGISTER
A1: REQUEST REGISTER — the Finance Desk queue
A2: Every request to finance, from a human or an agent. Intake: finance@maji-safi.com. Answers use LEAD. Nothing is answered twice, two different ways.
A4: ID | B4: Received | C4: From | D4: Type | E4: Request | F4: Needed by | G4: Status | H4: Answered | I4: Answer — L line | J4: Recorded in | K4: SLA met
A5: FD-001 | B5: 2026-09-21 | C5: Capital Brief (agent) | D5: document | E5: FY2025 and FY2026 statements prepared for a lender, not just URA | F5: Dec 2026 | G5: BLOCKED | H5: 2026-09-21 | I5: The statements do not exist and nobody keeps the books. They are hygiene, not the capital asset — the October close on 10 Nov is. Appoint an accountant this week and establish the year-end. | J5: requests/FD-001.md | K5: YES
A6: FD-002 | B6: 2026-09-21 | C6: Capital Brief (agent) | D6: decision | E6: Per-site cost: USD 80,000 or USD 20,000? 4x spread, blocks Wednesday | F6: 2026-09-23 | G6: DISPUTED | H6: 2026-09-21 | I6: Cannot certify either until the 80,000 is decomposed. Embargoed from all outbound. Send me the build-up and I rule in a day. | J6: requests/FD-002.md | K6: YES
A7: FD-003 | B7: 2026-09-21 | C7: Capital Brief (agent) | D7: approval | E7: May impact claims built on UNBS certification be used? | F7: 2026-09-23 | G7: EMBARGOED | H7: 2026-09-21 | I7: No. Embargoed until the certificate is verified filed. The plant spec is still sayable; certification and anything derived from it is not. | J7: requests/FD-003.md | K7: YES
A34: SLA — figure: same day (it is a lookup against canon). approval: same day. document: 3 working days or a committed date. decision: next 08:30 Ema sync or Monday cash roll.
A35: If a deadline will be missed: 'I don't know yet. I will have that by Thursday at noon.' Commit to a time and deliver. Never bluff.
A36: Worked daily against the FINANCE-DESK label, and again every Monday after the cash roll.

Sheet CANONICAL FIGURES
A1: CANONICAL FIGURES — the authority list
A2: IF A FIGURE IS NOT HERE WITH STATUS APPROVED, IT MAY NOT LEAVE THE BUILDING. No agent, no person, no document.
A3: Mirrored for agents as knowledge-base/05-finance-desk/canonical-figures.yaml. This tab is authoritative; if they disagree, the YAML is a bug.
A5: Figure | B5: Value | C5: Unit | D5: Basis | E5: As-of | F5: Status | G5: Owner | H5: Note / why blocked
A6: The 2026 capital ask | B6: — | C6: USD | D6: — | E6: 2026-10-05 | F6: DISPUTED | G6: Finance Desk | H6: Was APPROVED at USD 400,000 (five locations) on 21 Sep 2026. On ~1 Oct 2026 an agent desk re-based it to USD 100,000 and it went into outbound documents without founder or partner confirmation. The founder's own 2 Oct note (site 2 by March 2027, site 3 by May 2027) contradicts the five-sites-by-Q1-2027 basis of both figures. Per-site cost is itself DISPUTED (FD-002). Neither number may go outbound until the partners confirm one. Raised in "Maji Safi: Cash and Controls, October 2026" as decision 3.
A7: All-in cost per site | B7: — | C7: USD | D7: — | E7: 2026-09-21 | F7: DISPUTED | G7: Finance Desk | H7: Two sources disagree by 4x. The capital file states USD 80,000 all-in per site; the operations file states about USD 20,000 all-in and says that is the number to use with funders. Neither can be certified until the 80,000 is decomposed into plant-and-install versus fully-loaded site. Tracked as FD-002. Blocked by GAP-13 and GAP-16 (cost of sales and overheads are blended figures).
A8: UNBS certification status | B8: certified | C8: status | D8: Confirmed by the founder, 5 Oct 2026 | E8: 2026-10-05 | F8: APPROVED | G8: Sammy | H8: Founder confirmed certification on 5 Oct 2026. Add the certificate number and issue date here when filed, so any funder who checks gets the reference.
A9: Statutory financial year-end | B9: — | C9: date | D9: — | E9: 2026-09-21 | F9: UNVERIFIED | G9: Sammy | H9: Not established. Company incorporated October 2024. Until this is known we cannot say which periods FY2025 and FY2026 cover, whether statutory accounts are overdue with URA, or whether FY2026 statements can exist before the December lender deadline. Top blocking item. Tracked as FD-001.
A10: Full break-even, including the jar programme (month 1) | B10: 577 | C10: jars/day | D10: (fixed opex 8,163,542 + salaries 2,575,000 + depreciation 5,250,000 + jar programme 8,250,000) / contribution 1,616.82 per unit / 26 days | E10: 2026-09-08 | F10: APPROVED | G10: Finance Desk | H10: Planned month-1 output is 500/day, so the plan opens 77/day BELOW break-even.
A11: Cash break-even, including the jar programme (month 1) | B11: 452 | C11: jars/day | D11: Excludes depreciation | E11: 2026-09-08 | F11: APPROVED | G11: Finance Desk
A12: FY1 net revenue — PLAN | B12: 1807859712 | C12: UGX | D12: Year-1 model, net of VAT and excise per IFRS 15 | E12: 2026-09-08 | F12: APPROVED | G12: Finance Desk | H12: This is a FORECAST for a company that has not traded. It must always be stated as a plan, never as a result. Nothing may be described as revenue before 1 Oct 2026.
A13: FY1 lowest cash point — PLAN | B13: 17548449 | C13: UGX | D13: Month 1 of the Year-1 model | E13: 2026-09-08 | F13: APPROVED | G13: Finance Desk | H13: No facility, overdraft or committed tranche sits behind this.
A14: Customer deposits owed at month 12 — PLAN | B14: 157038750 | C14: UGX | D14: Cumulative jar deposits received, no returns modelled | E14: 2026-09-08 | F14: APPROVED | G14: Finance Desk | H14: Customers' money, repayable on jar return. Never present it as equity, headroom, distributable profit, or available as security to a lender.
A15: Minimum cash floor — policy | B15: 20000000 | C15: UGX | D15: Finance Desk policy | E15: 2026-09-21 | F15: APPROVED | G15: Finance Desk | H15: Internal policy. Below this the alarm fires and something gets cut.
A16: Plant and equipment at cost | B16: 315000000 | C16: UGX | D16: Year-1 model opening balance sheet | E16: 2026-09-08 | F16: APPROVED | G16: Finance Desk | H16: Already paid for. No Year-1 capex is modelled — see GAP-11.
A17: Trading status | B17: pre-trading until 2026-10-01 | C17: status | D17: Confirmed by founder | E17: 2026-09-21 | F17: APPROVED | G17: Sammy | H17: Say this plainly and early. Every financial figure before 1 Oct 2026 is a forecast. A funder who discovers it themselves has found a surprise; a funder told up front has been given a fact.
A18: FY2025 and FY2026 statutory financial statements | B18: — | C18: status | D18: — | E18: 2026-09-21 | F18: UNVERIFIED | G18: Sammy | H18: Nobody currently keeps the books. These statements appear never to have been prepared. Do not promise them to any lender or funder with a date until an accountant is appointed and the year-end is established. Tracked as FD-001.
A20: APPROVED — use it, and quote the as-of date.
A21: DISPUTED — two sources disagree and the Finance Desk has not ruled. Do not use it anywhere, internal or external.
A22: UNVERIFIED — not usable externally. Internally, mark it [UNVERIFIED].
A23: EMBARGOED — do not use it, and do not use anything derived from it. The reason is recorded.
A25: Authority granted by Sammy Ghedamu, founder, 21 September 2026, after a 4x spread on the headline ask sat live in two files during a week when eight funders were emailed.
